{
"meta":{"test_sets":[],"test_metrics":[],"learn_metrics":[{"best_value":"Min","name":"Logloss"}],"launch_mode":"Train","parameters":"","iteration_count":1000,"learn_sets":["learn"],"name":"experiment"},
"iterations":[
{"learn":[0.6916180812],"iteration":0,"passed_time":0.01182761788,"remaining_time":11.81579026},
{"learn":[0.690251387],"iteration":1,"passed_time":0.01723880439,"remaining_time":8.602163392},
{"learn":[0.6891312602],"iteration":2,"passed_time":0.02218630067,"remaining_time":7.373247257},
{"learn":[0.6877739512],"iteration":3,"passed_time":0.02720778399,"remaining_time":6.774738213},
{"learn":[0.6872725734],"iteration":4,"passed_time":0.03206403255,"remaining_time":6.380742477},
{"learn":[0.6857047425],"iteration":5,"passed_time":0.03600699869,"remaining_time":5.965159449},
{"learn":[0.6851014283],"iteration":6,"passed_time":0.04020302061,"remaining_time":5.703085638},
{"learn":[0.6838419227],"iteration":7,"passed_time":0.04637674273,"remaining_time":5.750716099},
{"learn":[0.6825604042],"iteration":8,"passed_time":0.0510644213,"remaining_time":5.622760168},
{"learn":[0.6808285309],"iteration":9,"passed_time":0.05658718841,"remaining_time":5.602131653},
{"learn":[0.6796078111],"iteration":10,"passed_time":0.06225806545,"remaining_time":5.597566066},
{"learn":[0.6783891316],"iteration":11,"passed_time":0.07047663943,"remaining_time":5.802576647},
{"learn":[0.6767621765],"iteration":12,"passed_time":0.075957065,"remaining_time":5.766894089},
{"learn":[0.6756460575],"iteration":13,"passed_time":0.08105219551,"remaining_time":5.708390341},
{"learn":[0.6743736068],"iteration":14,"passed_time":0.08673244632,"remaining_time":5.695430642},
{"learn":[0.6736040309],"iteration":15,"passed_time":0.0907383289,"remaining_time":5.580407227},
{"learn":[0.6729001646],"iteration":16,"passed_time":0.09564387522,"remaining_time":5.530466432},
{"learn":[0.6715995045],"iteration":17,"passed_time":0.101879283,"remaining_time":5.558080882},
{"learn":[0.6703559071],"iteration":18,"passed_time":0.1065038461,"remaining_time":5.49896174},
{"learn":[0.669138906],"iteration":19,"passed_time":0.1114052724,"remaining_time":5.458858348},
{"learn":[0.6686588211],"iteration":20,"passed_time":0.1173536945,"remaining_time":5.470917474},
{"learn":[0.6671673889],"iteration":21,"passed_time":0.12284949,"remaining_time":5.461218238},
{"learn":[0.6656698869],"iteration":22,"passed_time":0.1265950268,"remaining_time":5.377536572},
{"learn":[0.664644381],"iteration":23,"passed_time":0.1322105391,"remaining_time":5.376561925},
{"learn":[0.6633738024],"iteration":24,"passed_time":0.1365767481,"remaining_time":5.326493175},
{"learn":[0.6620268092],"iteration":25,"passed_time":0.1421992968,"remaining_time":5.327004426},
{"learn":[0.66140911],"iteration":26,"passed_time":0.1472680041,"remaining_time":5.30710252},
{"learn":[0.660728665],"iteration":27,"passed_time":0.1531589144,"remaining_time":5.316802316},
{"learn":[0.6594770592],"iteration":28,"passed_time":0.1610986464,"remaining_time":5.394027093},
{"learn":[0.6583040239],"iteration":29,"passed_time":0.1661378928,"remaining_time":5.371791869},
{"learn":[0.6572697214],"iteration":30,"passed_time":0.1708140505,"remaining_time":5.339316611},
{"learn":[0.6560559088],"iteration":31,"passed_time":0.1764501728,"remaining_time":5.337617727},
{"learn":[0.6551406824],"iteration":32,"passed_time":0.1802196344,"remaining_time":5.280981407},
{"learn":[0.654112311],"iteration":33,"passed_time":0.1854014626,"remaining_time":5.267582731},
{"learn":[0.6531208291],"iteration":34,"passed_time":0.1962393978,"remaining_time":5.41060054},
{"learn":[0.6518911012],"iteration":35,"passed_time":0.2014761307,"remaining_time":5.395083055},
{"learn":[0.6512503807],"iteration":36,"passed_time":0.2066429382,"remaining_time":5.378301337},
{"learn":[0.6505525868],"iteration":37,"passed_time":0.2118820375,"remaining_time":5.363961055},
{"learn":[0.6494921682],"iteration":38,"passed_time":0.2170281129,"remaining_time":5.347795295},
{"learn":[0.6485106996],"iteration":39,"passed_time":0.2219940833,"remaining_time":5.327858},
{"learn":[0.6477254087],"iteration":40,"passed_time":0.2268181059,"remaining_time":5.305330818},
{"learn":[0.6468083827],"iteration":41,"passed_time":0.2340449786,"remaining_time":5.338454511},
{"learn":[0.6463930763],"iteration":42,"passed_time":0.2401368611,"remaining_time":5.344441304},
{"learn":[0.645283208],"iteration":43,"passed_time":0.2468434384,"remaining_time":5.363234707},
{"learn":[0.6442729082],"iteration":44,"passed_time":0.2517599969,"remaining_time":5.342906601},
{"learn":[0.6433619048],"iteration":45,"passed_time":0.2570482922,"remaining_time":5.33095806},
{"learn":[0.6423312533],"iteration":46,"passed_time":0.2635907284,"remaining_time":5.344722641},
{"learn":[0.6412910695],"iteration":47,"passed_time":0.2693621815,"remaining_time":5.342349933},
{"learn":[0.6400288584],"iteration":48,"passed_time":0.2737872272,"remaining_time":5.313707206},
{"learn":[0.6397195392],"iteration":49,"passed_time":0.2781180335,"remaining_time":5.284242636},
{"learn":[0.6384638335],"iteration":50,"passed_time":0.2832540828,"remaining_time":5.27074754},
{"learn":[0.6370974429],"iteration":51,"passed_time":0.2906527492,"remaining_time":5.298823197},
{"learn":[0.6356376007],"iteration":52,"passed_time":0.2973724187,"remaining_time":5.313427935},
{"learn":[0.6341432118],"iteration":53,"passed_time":0.3035892295,"remaining_time":5.318433539},
{"learn":[0.6330362818],"iteration":54,"passed_time":0.3089686213,"remaining_time":5.308642675},
{"learn":[0.632446913],"iteration":55,"passed_time":0.314318679,"remaining_time":5.298514875},
{"learn":[0.631801273],"iteration":56,"passed_time":0.4507560974,"remaining_time":7.457245611},
{"learn":[0.6306086133],"iteration":57,"passed_time":0.4997661005,"remaining_time":8.116890804},
{"learn":[0.6297924461],"iteration":58,"passed_time":0.5610549864,"remaining_time":8.948351562},
{"learn":[0.6288084335],"iteration":59,"passed_time":0.5647319647,"remaining_time":8.847467447},
{"learn":[0.6278820374],"iteration":60,"passed_time":0.5683732089,"remaining_time":8.74922038},
{"learn":[0.6267276285],"iteration":61,"passed_time":0.5722371009,"remaining_time":8.657393559},
{"learn":[0.6256682953],"iteration":62,"passed_time":0.5790250831,"remaining_time":8.611849252},
{"learn":[0.6251596579],"iteration":63,"passed_time":0.5827159402,"remaining_time":8.522220626},
{"learn":[0.6242252125],"iteration":64,"passed_time":0.659218775,"remaining_time":9.482608533},
{"learn":[0.6232607034],"iteration":65,"passed_time":0.6658343744,"remaining_time":9.422565237},
{"learn":[0.6221841403],"iteration":66,"passed_time":0.7094917656,"remaining_time":9.879937572},
{"learn":[0.6208681271],"iteration":67,"passed_time":0.7190581053,"remaining_time":9.855325797},
{"learn":[0.6196930141],"iteration":68,"passed_time":0.72926626,"remaining_time":9.839809972},
{"learn":[0.6188144441],"iteration":69,"passed_time":0.7366177785,"remaining_time":9.786493343},
{"learn":[0.6183571217],"iteration":70,"passed_time":0.740896325,"remaining_time":9.694263182},
{"learn":[0.6174033477],"iteration":71,"passed_time":0.7460939677,"remaining_time":9.616322251},
{"learn":[0.6170081107],"iteration":72,"passed_time":0.7509939723,"remaining_time":9.536594689},
{"learn":[0.6167322447],"iteration":73,"passed_time":0.7564817773,"remaining_time":9.466244943},
{"learn":[0.6158582342],"iteration":74,"passed_time":0.7630629865,"remaining_time":9.411110166},
{"learn":[0.614770559],"iteration":75,"passed_time":0.7677356827,"remaining_time":9.334049616},
{"learn":[0.6137412698],"iteration":76,"passed_time":0.7767191461,"remaining_time":9.310542491},
{"learn":[0.6125228789],"iteration":77,"passed_time":0.7808424198,"remaining_time":9.229957834},
{"learn":[0.61124634],"iteration":78,"passed_time":0.7864415885,"remaining_time":9.168515228},
{"learn":[0.6108145504],"iteration":79,"passed_time":0.7962906168,"remaining_time":9.157342094},
{"learn":[0.6097160183],"iteration":80,"passed_time":0.8022337268,"remaining_time":9.101886357},
{"learn":[0.6086378978],"iteration":81,"passed_time":0.8068536362,"remaining_time":9.032824854},
{"learn":[0.6075652534],"iteration":82,"passed_time":0.8109454283,"remaining_time":8.959481419},
{"learn":[0.6068063858],"iteration":83,"passed_time":0.8151099796,"remaining_time":8.888580254},
{"learn":[0.6061173589],"iteration":84,"passed_time":0.81917607,"remaining_time":8.818189459},
{"learn":[0.6048720358],"iteration":85,"passed_time":0.8278176938,"remaining_time":8.797969444},
{"learn":[0.604065977],"iteration":86,"passed_time":0.8323246719,"remaining_time":8.73462558},
{"learn":[0.6029407125],"iteration":87,"passed_time":0.8372889973,"remaining_time":8.677358699},
{"learn":[0.6026397127],"iteration":88,"passed_time":0.8419510108,"remaining_time":8.618172706},
{"learn":[0.6016923658],"iteration":89,"passed_time":0.8481608637,"remaining_time":8.575848733},
{"learn":[0.6008421337],"iteration":90,"passed_time":0.8538190157,"remaining_time":8.52880753},
{"learn":[0.6003524672],"iteration":91,"passed_time":0.8596720794,"remaining_time":8.484589653},
{"learn":[0.5993229824],"iteration":92,"passed_time":0.8658702411,"remaining_time":8.444562459},
{"learn":[0.5982084153],"iteration":93,"passed_time":0.8706982822,"remaining_time":8.392049401},
{"learn":[0.5973630222],"iteration":94,"passed_time":0.8739334168,"remaining_time":8.325365707},
{"learn":[0.5964713786],"iteration":95,"passed_time":0.8789778635,"remaining_time":8.277041548},
{"learn":[0.5955339709],"iteration":96,"passed_time":0.8853723239,"remaining_time":8.242177407},
{"learn":[0.5947492945],"iteration":97,"passed_time":0.8892476283,"remaining_time":8.184707763},
{"learn":[0.5937413391],"iteration":98,"passed_time":0.8935327478,"remaining_time":8.132050563},
{"learn":[0.5926504527],"iteration":99,"passed_time":0.9000277893,"remaining_time":8.100250104},
{"learn":[0.5919696805],"iteration":100,"passed_time":0.9050146391,"remaining_time":8.055526342},
{"learn":[0.5909734915],"iteration":101,"passed_time":0.9117530962,"remaining_time":8.027002749},
{"learn":[0.590015019],"iteration":102,"passed_time":0.9166561976,"remaining_time":7.982918536},
{"learn":[0.5893079467],"iteration":103,"passed_time":0.9209691804,"remaining_time":7.934503708},
{"learn":[0.5884324892],"iteration":104,"passed_time":0.9247348076,"remaining_time":7.88226336},
{"learn":[0.587722009],"iteration":105,"passed_time":0.9303412457,"remaining_time":7.846462959},
{"learn":[0.5870112451],"iteration":106,"passed_time":0.9351838141,"remaining_time":7.804851832},
{"learn":[0.5857355539],"iteration":107,"passed_time":0.9383847187,"remaining_time":7.750362677},
{"learn":[0.5845269655],"iteration":108,"passed_time":0.9434928343,"remaining_time":7.712404728},
{"learn":[0.5835260959],"iteration":109,"passed_time":0.9465964049,"remaining_time":7.658825458},
{"learn":[0.5824912218],"iteration":110,"passed_time":0.9510660732,"remaining_time":7.617096749},
{"learn":[0.5815426564],"iteration":111,"passed_time":0.9563234244,"remaining_time":7.582278579},
{"learn":[0.5808271986],"iteration":112,"passed_time":0.9617473533,"remaining_time":7.549291171},
{"learn":[0.5797608384],"iteration":113,"passed_time":0.9675585014,"remaining_time":7.519796774},
{"learn":[0.5786621582],"iteration":114,"passed_time":0.9732767687,"remaining_time":7.489999481},
{"learn":[0.5776957483],"iteration":115,"passed_time":0.9765478848,"remaining_time":7.441968364},
{"learn":[0.5765674423],"iteration":116,"passed_time":0.9815623952,"remaining_time":7.407859786},
{"learn":[0.575643083],"iteration":117,"passed_time":0.9857773029,"remaining_time":7.368267637},
{"learn":[0.5748292997],"iteration":118,"passed_time":0.989863881,"remaining_time":7.328319993},
{"learn":[0.5735934741],"iteration":119,"passed_time":0.9967121158,"remaining_time":7.309222182},
{"learn":[0.5727949181],"iteration":120,"passed_time":1.002041153,"remaining_time":7.279290687},
{"learn":[0.5723013486],"iteration":121,"passed_time":1.006535525,"remaining_time":7.24375566},
{"learn":[0.5712342323],"iteration":122,"passed_time":1.012124777,"remaining_time":7.216531946},
{"learn":[0.5705341217],"iteration":123,"passed_time":1.016882054,"remaining_time":7.18377967},
{"learn":[0.5697302239],"iteration":124,"passed_time":1.020572739,"remaining_time":7.14400917},
{"learn":[0.5690338065],"iteration":125,"passed_time":1.024500835,"remaining_time":7.106458172},
{"learn":[0.5683349343],"iteration":126,"passed_time":1.028109487,"remaining_time":7.067240806},
{"learn":[0.5675525803],"iteration":127,"passed_time":1.033593688,"remaining_time":7.041356997},
{"learn":[0.5665118457],"iteration":128,"passed_time":1.037621758,"remaining_time":7.005957758},
{"learn":[0.56570412],"iteration":129,"passed_time":1.040858435,"remaining_time":6.965744911},
{"learn":[0.5649109461],"iteration":130,"passed_time":1.043938207,"remaining_time":6.925055742},
{"learn":[0.5642008969],"iteration":131,"passed_time":1.049315061,"remaining_time":6.90004146},
{"learn":[0.56346387],"iteration":132,"passed_time":1.052797014,"remaining_time":6.862970006},
{"learn":[0.562699856],"iteration":133,"passed_time":1.056185047,"remaining_time":6.825792914},
{"learn":[0.5619592385],"iteration":134,"passed_time":1.059459067,"remaining_time":6.788385877},
{"learn":[0.5610224307],"iteration":135,"passed_time":1.066526517,"remaining_time":6.775580223},
{"learn":[0.5608446019],"iteration":136,"passed_time":1.073941952,"remaining_time":6.765050398},
{"learn":[0.5601568112],"iteration":137,"passed_time":1.080093214,"remaining_time":6.746669209},
{"learn":[0.5594688356],"iteration":138,"passed_time":1.084052649,"remaining_time":6.714887275},
{"learn":[0.5585804659],"iteration":139,"passed_time":1.089082431,"remaining_time":6.69007779},
{"learn":[0.5575881799],"iteration":140,"passed_time":1.097232114,"remaining_time":6.684555931},
{"learn":[0.5568347551],"iteration":141,"passed_time":1.102943602,"remaining_time":6.664264861},
{"learn":[0.5563696579],"iteration":142,"passed_time":1.10710502,"remaining_time":6.634888128},
{"learn":[0.5557031372],"iteration":143,"passed_time":1.111066113,"remaining_time":6.604670785},
{"learn":[0.5549735902],"iteration":144,"passed_time":1.115803766,"remaining_time":6.57939462},
{"learn":[0.5540644687],"iteration":145,"passed_time":1.118754626,"remaining_time":6.543948291},
{"learn":[0.553147226],"iteration":146,"passed_time":1.12541674,"remaining_time":6.530479452},
{"learn":[0.5522879263],"iteration":147,"passed_time":1.131730036,"remaining_time":6.51509453},
{"learn":[0.5515499016],"iteration":148,"passed_time":1.136185934,"remaining_time":6.48922302},
{"learn":[0.5508480878],"iteration":149,"passed_time":1.140633084,"remaining_time":6.463587478},
{"learn":[0.5501166941],"iteration":150,"passed_time":1.146683886,"remaining_time":6.447249133},
{"learn":[0.5492631997],"iteration":151,"passed_time":1.150585403,"remaining_time":6.419055405},
{"learn":[0.5482139267],"iteration":152,"passed_time":1.156515693,"remaining_time":6.402410406},
{"learn":[0.5473216055],"iteration":153,"passed_time":1.161784854,"remaining_time":6.382272642},
{"learn":[0.5462106339],"iteration":154,"passed_time":1.16522502,"remaining_time":6.352355755},
{"learn":[0.5455424272],"iteration":155,"passed_time":1.169928012,"remaining_time":6.329610524},
{"learn":[0.545132132],"iteration":156,"passed_time":1.173940935,"remaining_time":6.30338986},
{"learn":[0.5444483349],"iteration":157,"passed_time":1.177589343,"remaining_time":6.275507762},
{"learn":[0.5436554264],"iteration":158,"passed_time":1.18181805,"remaining_time":6.250999872},
{"learn":[0.5428090035],"iteration":159,"passed_time":1.18678791,"remaining_time":6.230636526},
{"learn":[0.5421683534],"iteration":160,"passed_time":1.190736416,"remaining_time":6.205141942},
{"learn":[0.5413978332],"iteration":161,"passed_time":1.193824689,"remaining_time":6.175463513},
{"learn":[0.5405732973],"iteration":162,"passed_time":1.198930223,"remaining_time":6.156469916},
{"learn":[0.5395919476],"iteration":163,"passed_time":1.205386856,"remaining_time":6.144532998},
{"learn":[0.538783425],"iteration":164,"passed_time":1.209660953,"remaining_time":6.121617548},
{"learn":[0.5378345858],"iteration":165,"passed_time":1.216783959,"remaining_time":6.113239891},
{"learn":[0.5368276277],"iteration":166,"passed_time":1.222413469,"remaining_time":6.097427661},
{"learn":[0.53618001],"iteration":167,"passed_time":1.228024101,"remaining_time":6.081643169},
{"learn":[0.535063317],"iteration":168,"passed_time":1.233785408,"remaining_time":6.066719967},
{"learn":[0.5349647833],"iteration":169,"passed_time":1.237723148,"remaining_time":6.043001253},
{"learn":[0.5338868504],"iteration":170,"passed_time":1.243202661,"remaining_time":6.026988341},
{"learn":[0.5332798687],"iteration":171,"passed_time":1.246307205,"remaining_time":5.999664918},
{"learn":[0.5327660927],"iteration":172,"passed_time":1.252215645,"remaining_time":5.986025077},
{"learn":[0.5321592595],"iteration":173,"passed_time":1.259739299,"remaining_time":5.980141728},
{"learn":[0.5315487335],"iteration":174,"passed_time":1.264304342,"remaining_time":5.960291899},
{"learn":[0.530899448],"iteration":175,"passed_time":1.269973774,"remaining_time":5.945786306},
{"learn":[0.5302009522],"iteration":176,"passed_time":1.27526545,"remaining_time":5.929624099},
{"learn":[0.5293879228],"iteration":177,"passed_time":1.281536254,"remaining_time":5.918105622},
{"learn":[0.5287121661],"iteration":178,"passed_time":1.286174175,"remaining_time":5.899156412},
{"learn":[0.5281598573],"iteration":179,"passed_time":1.301746213,"remaining_time":5.930177193},
{"learn":[0.5276920829],"iteration":180,"passed_time":1.305531755,"remaining_time":5.907350867},
{"learn":[0.5267042032],"iteration":181,"passed_time":1.310863529,"remaining_time":5.891683335},
{"learn":[0.5263804462],"iteration":182,"passed_time":1.31910914,"remaining_time":5.889137527},
{"learn":[0.5254459944],"iteration":183,"passed_time":1.32644915,"remaining_time":5.882513622},
{"learn":[0.5249759213],"iteration":184,"passed_time":1.331767639,"remaining_time":5.866976356},
{"learn":[0.5240531078],"iteration":185,"passed_time":1.337175528,"remaining_time":5.851940214},
{"learn":[0.5234510347],"iteration":186,"passed_time":1.344131283,"remaining_time":5.843736542},
{"learn":[0.5229674004],"iteration":187,"passed_time":1.349134151,"remaining_time":5.827111332},
{"learn":[0.5223415461],"iteration":188,"passed_time":1.355563478,"remaining_time":5.816730055},
{"learn":[0.5217514855],"iteration":189,"passed_time":1.360174683,"remaining_time":5.798639439},
{"learn":[0.5209749264],"iteration":190,"passed_time":1.365368439,"remaining_time":5.783157419},
{"learn":[0.5202566297],"iteration":191,"passed_time":1.371799933,"remaining_time":5.772991385},
{"learn":[0.5200042824],"iteration":192,"passed_time":1.376754192,"remaining_time":5.756687219},
{"learn":[0.5193479205],"iteration":193,"passed_time":1.381359729,"remaining_time":5.739051245},
{"learn":[0.518598349],"iteration":194,"passed_time":1.386195819,"remaining_time":5.722500689},
{"learn":[0.5184524633],"iteration":195,"passed_time":1.389480347,"remaining_time":5.699705097},
{"learn":[0.5173693962],"iteration":196,"passed_time":1.39520813,"remaining_time":5.687066643},
{"learn":[0.5167501602],"iteration":197,"passed_time":1.405399972,"remaining_time":5.692579684},
{"learn":[0.5162146235],"iteration":198,"passed_time":1.409052322,"remaining_time":5.671612613},
{"learn":[0.5154873519],"iteration":199,"passed_time":1.414548856,"remaining_time":5.658195425},
{"learn":[0.5146808768],"iteration":200,"passed_time":1.423901873,"remaining_time":5.660187047},
{"learn":[0.5142009115],"iteration":201,"passed_time":1.430537716,"remaining_time":5.651332164},
{"learn":[0.5138618394],"iteration":202,"passed_time":1.435407741,"remaining_time":5.635566353},
{"learn":[0.5130752866],"iteration":203,"passed_time":1.440490464,"remaining_time":5.620737303},
{"learn":[0.5126852989],"iteration":204,"passed_time":1.446477041,"remaining_time":5.609508525},
{"learn":[0.5118616378],"iteration":205,"passed_time":1.452287883,"remaining_time":5.597653295},
{"learn":[0.5113004126],"iteration":206,"passed_time":1.467565477,"remaining_time":5.622122818},
{"learn":[0.5110385197],"iteration":207,"passed_time":1.478312912,"remaining_time":5.628960703},
{"learn":[0.5100296416],"iteration":208,"passed_time":1.485290565,"remaining_time":5.621362856},
{"learn":[0.5093818472],"iteration":209,"passed_time":1.491835476,"remaining_time":5.612142982},
{"learn":[0.5087951565],"iteration":210,"passed_time":1.502032577,"remaining_time":5.61660523},
{"learn":[0.5079166128],"iteration":211,"passed_time":1.507503701,"remaining_time":5.603362812},
{"learn":[0.5070290897],"iteration":212,"passed_time":1.514777518,"remaining_time":5.596854023},
{"learn":[0.506684566],"iteration":213,"passed_time":1.520175642,"remaining_time":5.583448852},
{"learn":[0.5060396371],"iteration":214,"passed_time":1.524221986,"remaining_time":5.565182599},
{"learn":[0.5051691532],"iteration":215,"passed_time":1.530047896,"remaining_time":5.55350718},
{"learn":[0.5048333031],"iteration":216,"passed_time":1.535652674,"remaining_time":5.541087758},
{"learn":[0.5040297917],"iteration":217,"passed_time":1.541482696,"remaining_time":5.529538846},
{"learn":[0.5032980817],"iteration":218,"passed_time":1.546475579,"remaining_time":5.515056745},
{"learn":[0.502675477],"iteration":219,"passed_time":1.552938593,"remaining_time":5.505873192},
{"learn":[0.5022197465],"iteration":220,"passed_time":1.564732645,"remaining_time":5.515505566},
{"learn":[0.5013728815],"iteration":221,"passed_time":1.572928389,"remaining_time":5.512334623},
{"learn":[0.5005515648],"iteration":222,"passed_time":1.577487925,"remaining_time":5.49644896},
{"learn":[0.4997112928],"iteration":223,"passed_time":1.587763119,"remaining_time":5.500465092},
{"learn":[0.4989995912],"iteration":224,"passed_time":1.594773417,"remaining_time":5.493108437},
{"learn":[0.49856658],"iteration":225,"passed_time":1.600397162,"remaining_time":5.48100621},
{"learn":[0.4977613003],"iteration":226,"passed_time":1.604905106,"remaining_time":5.465161439},
{"learn":[0.4971701139],"iteration":227,"passed_time":1.61364342,"remaining_time":5.463740001},
{"learn":[0.4963959455],"iteration":228,"passed_time":1.621528252,"remaining_time":5.459381146},
{"learn":[0.4958005801],"iteration":229,"passed_time":1.628008981,"remaining_time":5.450290936},
{"learn":[0.4954394378],"iteration":230,"passed_time":1.634634852,"remaining_time":5.4417065},
{"learn":[0.4947607308],"iteration":231,"passed_time":1.641046356,"remaining_time":5.432429317},
{"learn":[0.4941824045],"iteration":232,"passed_time":1.648843715,"remaining_time":5.427738754},
{"learn":[0.4932750883],"iteration":233,"passed_time":1.659851355,"remaining_time":5.433530504},
{"learn":[0.4928057271],"iteration":234,"passed_time":1.666613919,"remaining_time":5.425360205},
{"learn":[0.4922013515],"iteration":235,"passed_time":1.678337915,"remaining_time":5.43326342},
{"learn":[0.4914837446],"iteration":236,"passed_time":1.685098511,"remaining_time":5.42502179},
{"learn":[0.4908163349],"iteration":237,"passed_time":1.690784983,"remaining_time":5.4133536},
{"learn":[0.4901917378],"iteration":238,"passed_time":1.69866607,"remaining_time":5.408723343},
{"learn":[0.4896105075],"iteration":239,"passed_time":1.702724455,"remaining_time":5.391960775},
{"learn":[0.4888046814],"iteration":240,"passed_time":1.711037938,"remaining_time":5.388704542},
{"learn":[0.4882094286],"iteration":241,"passed_time":1.72035676,"remaining_time":5.388555473},
{"learn":[0.4876245558],"iteration":242,"passed_time":1.726890763,"remaining_time":5.379655586},
{"learn":[0.4871122903],"iteration":243,"passed_time":1.733268488,"remaining_time":5.370290888},
{"learn":[0.4865506987],"iteration":244,"passed_time":1.73940398,"remaining_time":5.360204102},
{"learn":[0.4858328391],"iteration":245,"passed_time":1.744893795,"remaining_time":5.348170411},
{"learn":[0.4851889246],"iteration":246,"passed_time":1.750088281,"remaining_time":5.335289374},
{"learn":[0.4844410475],"iteration":247,"passed_time":1.757910555,"remaining_time":5.330438456},
{"learn":[0.4838494107],"iteration":248,"passed_time":1.761990821,"remaining_time":5.314277536},
{"learn":[0.4831010523],"iteration":249,"passed_time":1.768402781,"remaining_time":5.305208344},
{"learn":[0.4824708954],"iteration":250,"passed_time":1.777695879,"remaining_time":5.304757821},
{"learn":[0.4817783071],"iteration":251,"passed_time":1.783263908,"remaining_time":5.293180173},
{"learn":[0.4814827497],"iteration":252,"passed_time":1.790558775,"remaining_time":5.286748637},
{"learn":[0.4806631594],"iteration":253,"passed_time":1.795960129,"remaining_time":5.274749042},
{"learn":[0.4803828167],"iteration":254,"passed_time":1.799810434,"remaining_time":5.258269699},
{"learn":[0.4798919978],"iteration":255,"passed_time":1.804951496,"remaining_time":5.245640285},
{"learn":[0.4789991909],"iteration":256,"passed_time":1.811756829,"remaining_time":5.237880638},
{"learn":[0.4782475973],"iteration":257,"passed_time":1.816982548,"remaining_time":5.225585466},
{"learn":[0.4776753066],"iteration":258,"passed_time":1.82302576,"remaining_time":5.215683738},
{"learn":[0.4774465738],"iteration":259,"passed_time":1.827058333,"remaining_time":5.200089101},
{"learn":[0.4770640047],"iteration":260,"passed_time":1.831825073,"remaining_time":5.186661797},
{"learn":[0.4766385721],"iteration":261,"passed_time":1.838158653,"remaining_time":5.177714068},
{"learn":[0.4759636334],"iteration":262,"passed_time":1.842416799,"remaining_time":5.162970269},
{"learn":[0.4754904089],"iteration":263,"passed_time":1.847762524,"remaining_time":5.151337945},
{"learn":[0.474964271],"iteration":264,"passed_time":1.856647781,"remaining_time":5.149570262},
{"learn":[0.4742728858],"iteration":265,"passed_time":1.862476672,"remaining_time":5.139315329},
{"learn":[0.4738195682],"iteration":266,"passed_time":1.867266545,"remaining_time":5.126241115},
{"learn":[0.4733973466],"iteration":267,"passed_time":1.874612644,"remaining_time":5.120210656},
{"learn":[0.4727109373],"iteration":268,"passed_time":1.880904086,"remaining_time":5.111304411},
{"learn":[0.4720160796],"iteration":269,"passed_time":1.884414108,"remaining_time":5.094897402},
{"learn":[0.4714771564],"iteration":270,"passed_time":1.888943001,"remaining_time":5.081326376},
{"learn":[0.4710827702],"iteration":271,"passed_time":1.896449021,"remaining_time":5.075790028},
{"learn":[0.4706032773],"iteration":272,"passed_time":1.912643486,"remaining_time":5.09337661},
{"learn":[0.4697130146],"iteration":273,"passed_time":1.92439136,"remaining_time":5.09893477},
{"learn":[0.4691771865],"iteration":274,"passed_time":1.929617347,"remaining_time":5.087173007},
{"learn":[0.4687219803],"iteration":275,"passed_time":1.933165635,"remaining_time":5.07105768},
{"learn":[0.4680692896],"iteration":276,"passed_time":1.94024978,"remaining_time":5.064262062},
{"learn":[0.467561086],"iteration":277,"passed_time":1.944826116,"remaining_time":5.05095128},
{"learn":[0.466997395],"iteration":278,"passed_time":1.962252751,"remaining_time":5.070911232},
{"learn":[0.4664353298],"iteration":279,"passed_time":1.967554503,"remaining_time":5.059425865},
{"learn":[0.4659089777],"iteration":280,"passed_time":1.974281326,"remaining_time":5.051630867},
{"learn":[0.4652794213],"iteration":281,"passed_time":1.979251077,"remaining_time":5.039369763},
{"learn":[0.4645201685],"iteration":282,"passed_time":1.984481069,"remaining_time":5.027819527},
{"learn":[0.4638383918],"iteration":283,"passed_time":1.989136975,"remaining_time":5.014866458},
{"learn":[0.4632916715],"iteration":284,"passed_time":1.997500224,"remaining_time":5.011272492},
{"learn":[0.4628201149],"iteration":285,"passed_time":2.001487706,"remaining_time":4.996721055},
{"learn":[0.4621050832],"iteration":286,"passed_time":2.01611861,"remaining_time":5.008684909},
{"learn":[0.4612976048],"iteration":287,"passed_time":2.023184137,"remaining_time":5.001760782},
{"learn":[0.4608855855],"iteration":288,"passed_time":2.029474984,"remaining_time":4.992929805},
{"learn":[0.4602790221],"iteration":289,"passed_time":2.035528503,"remaining_time":4.983535301},
{"learn":[0.4597513058],"iteration":290,"passed_time":2.047622631,"remaining_time":4.988881255},
{"learn":[0.4591707433],"iteration":291,"passed_time":2.055779619,"remaining_time":4.984561543},
{"learn":[0.4586709418],"iteration":292,"passed_time":2.062002985,"remaining_time":4.975549866},
{"learn":[0.4580086911],"iteration":293,"passed_time":2.067720416,"remaining_time":4.965342223},
{"learn":[0.457517731],"iteration":294,"passed_time":2.074412363,"remaining_time":4.957493951},
{"learn":[0.4569136059],"iteration":295,"passed_time":2.07930126,"remaining_time":4.945365159},
{"learn":[0.4563036418],"iteration":296,"passed_time":2.085038225,"remaining_time":4.9352925},
{"learn":[0.4556167523],"iteration":297,"passed_time":2.095314769,"remaining_time":4.935942845},
{"learn":[0.4550663122],"iteration":298,"passed_time":2.099752562,"remaining_time":4.922831256},
{"learn":[0.4544669975],"iteration":299,"passed_time":2.108306732,"remaining_time":4.919382374},
{"learn":[0.4541075715],"iteration":300,"passed_time":2.114122067,"remaining_time":4.909539285},
{"learn":[0.4538459193],"iteration":301,"passed_time":2.120273815,"remaining_time":4.900500406},
{"learn":[0.4532986063],"iteration":302,"passed_time":2.126578342,"remaining_time":4.891832027},
{"learn":[0.452751057],"iteration":303,"passed_time":2.13103448,"remaining_time":4.878947363},
{"learn":[0.4524403281],"iteration":304,"passed_time":2.141765909,"remaining_time":4.8804174},
{"learn":[0.451872457],"iteration":305,"passed_time":2.146791737,"remaining_time":4.868867535},
{"learn":[0.4512746522],"iteration":306,"passed_time":2.155748739,"remaining_time":4.866234124},
{"learn":[0.4508180751],"iteration":307,"passed_time":2.193109053,"remaining_time":4.927374884},
{"learn":[0.4506685303],"iteration":308,"passed_time":2.200529236,"remaining_time":4.920924602},
{"learn":[0.4498546764],"iteration":309,"passed_time":2.205321279,"remaining_time":4.90861833},
{"learn":[0.4494535007],"iteration":310,"passed_time":2.211928411,"remaining_time":4.900381593},
{"learn":[0.4486860567],"iteration":311,"passed_time":2.216137339,"remaining_time":4.886866952},
{"learn":[0.4479615688],"iteration":312,"passed_time":2.224555156,"remaining_time":4.882649815},
{"learn":[0.4474124809],"iteration":313,"passed_time":2.230981372,"remaining_time":4.874054845},
{"learn":[0.4468905782],"iteration":314,"passed_time":2.238058961,"remaining_time":4.866890121},
{"learn":[0.4462629733],"iteration":315,"passed_time":2.243446941,"remaining_time":4.856068696},
{"learn":[0.4456833469],"iteration":316,"passed_time":2.25134486,"remaining_time":4.850689399},
{"learn":[0.4451709975],"iteration":317,"passed_time":2.255973206,"remaining_time":4.83828216},
{"learn":[0.444631879],"iteration":318,"passed_time":2.272170977,"remaining_time":4.850622054},
{"learn":[0.4440670024],"iteration":319,"passed_time":2.281386268,"remaining_time":4.847945819},
{"learn":[0.4436478626],"iteration":320,"passed_time":2.298848862,"remaining_time":4.862674072},
{"learn":[0.4431842897],"iteration":321,"passed_time":2.303363389,"remaining_time":4.849939061},
{"learn":[0.4429966311],"iteration":322,"passed_time":2.313176078,"remaining_time":4.848359768},
{"learn":[0.4423895578],"iteration":323,"passed_time":2.318344969,"remaining_time":4.837040738},
{"learn":[0.4415911039],"iteration":324,"passed_time":2.327896308,"remaining_time":4.834861562},
{"learn":[0.4409626513],"iteration":325,"passed_time":2.337335617,"remaining_time":4.83240554},
{"learn":[0.4405639205],"iteration":326,"passed_time":2.347488645,"remaining_time":4.831375714},
{"learn":[0.4402294413],"iteration":327,"passed_time":2.358534206,"remaining_time":4.832118861},
{"learn":[0.4399315549],"iteration":328,"passed_time":2.38371436,"remaining_time":4.861618041},
{"learn":[0.4396075043],"iteration":329,"passed_time":2.387985449,"remaining_time":4.848334094},
{"learn":[0.4390690459],"iteration":330,"passed_time":2.393214049,"remaining_time":4.837039875},
{"learn":[0.4385407302],"iteration":331,"passed_time":2.400052048,"remaining_time":4.829020386},
{"learn":[0.4380582825],"iteration":332,"passed_time":2.407827572,"remaining_time":4.822885857},
{"learn":[0.4377324979],"iteration":333,"passed_time":2.418252694,"remaining_time":4.822024832},
{"learn":[0.4374228142],"iteration":334,"passed_time":2.425358982,"remaining_time":4.814518575},
{"learn":[0.4368874629],"iteration":335,"passed_time":2.431471149,"remaining_time":4.805050127},
{"learn":[0.4364130486],"iteration":336,"passed_time":2.438876533,"remaining_time":4.798145821},
{"learn":[0.4356799556],"iteration":337,"passed_time":2.464726018,"remaining_time":4.827362793},
{"learn":[0.4350512668],"iteration":338,"passed_time":2.478956342,"remaining_time":4.833599239},
{"learn":[0.4345140203],"iteration":339,"passed_time":2.498315834,"remaining_time":4.849671914},
{"learn":[0.4339935989],"iteration":340,"passed_time":2.508876812,"remaining_time":4.848533195},
{"learn":[0.433529728],"iteration":341,"passed_time":2.514258702,"remaining_time":4.83737493},
{"learn":[0.4332765374],"iteration":342,"passed_time":2.518067336,"remaining_time":4.823236851},
{"learn":[0.4326768275],"iteration":343,"passed_time":2.556398268,"remaining_time":4.874992046},
{"learn":[0.4324155626],"iteration":344,"passed_time":2.565101081,"remaining_time":4.869974516},
{"learn":[0.4318880516],"iteration":345,"passed_time":2.583833919,"remaining_time":4.883894171},
{"learn":[0.4312064416],"iteration":346,"passed_time":2.591924142,"remaining_time":4.877597881},
{"learn":[0.4309261728],"iteration":347,"passed_time":2.606259008,"remaining_time":4.882991015},
{"learn":[0.4303229893],"iteration":348,"passed_time":2.616725583,"remaining_time":4.881055456},
{"learn":[0.4301410593],"iteration":349,"passed_time":2.62206546,"remaining_time":4.86955014},
{"learn":[0.4293842437],"iteration":350,"passed_time":2.629271841,"remaining_time":4.861531124},
{"learn":[0.4289633753],"iteration":351,"passed_time":2.635378637,"remaining_time":4.851492491},
{"learn":[0.4286896752],"iteration":352,"passed_time":2.65348523,"remaining_time":4.863470096},
{"learn":[0.4282276432],"iteration":353,"passed_time":2.663870998,"remaining_time":4.861188318},
{"learn":[0.4277745496],"iteration":354,"passed_time":2.668903719,"remaining_time":4.849134926},
{"learn":[0.4270900929],"iteration":355,"passed_time":2.688140841,"remaining_time":4.862816578},
{"learn":[0.4266814303],"iteration":356,"passed_time":2.698632613,"remaining_time":4.860562382},
{"learn":[0.4260605982],"iteration":357,"passed_time":2.705738433,"remaining_time":4.852190151},
{"learn":[0.4257228617],"iteration":358,"passed_time":2.708798388,"remaining_time":4.836601021},
{"learn":[0.425138181],"iteration":359,"passed_time":2.728376298,"remaining_time":4.850446752},
{"learn":[0.4248475642],"iteration":360,"passed_time":2.758174835,"remaining_time":4.88219867},
{"learn":[0.4244477296],"iteration":361,"passed_time":2.771089118,"remaining_time":4.883853198},
{"learn":[0.4240423187],"iteration":362,"passed_time":2.793558875,"remaining_time":4.902195601},
{"learn":[0.4235815759],"iteration":363,"passed_time":2.810768659,"remaining_time":4.911123261},
{"learn":[0.423057416],"iteration":364,"passed_time":2.824984849,"remaining_time":4.914699669},
{"learn":[0.4222439351],"iteration":365,"passed_time":2.8337281,"remaining_time":4.908698403},
{"learn":[0.4216219717],"iteration":366,"passed_time":2.845612146,"remaining_time":4.908099423},
{"learn":[0.421160762],"iteration":367,"passed_time":2.858298331,"remaining_time":4.908816699},
{"learn":[0.420557234],"iteration":368,"passed_time":2.870382218,"remaining_time":4.908431381},
{"learn":[0.4202820504],"iteration":369,"passed_time":2.879503375,"remaining_time":4.902938179},
{"learn":[0.4197277791],"iteration":370,"passed_time":2.892198563,"remaining_time":4.903484896},
{"learn":[0.4193480677],"iteration":371,"passed_time":2.97108034,"remaining_time":5.015694768},
{"learn":[0.4189490433],"iteration":372,"passed_time":3.01906818,"remaining_time":5.074948388},
{"learn":[0.4182246195],"iteration":373,"passed_time":3.036121371,"remaining_time":5.08185021},
{"learn":[0.4176069929],"iteration":374,"passed_time":3.065274618,"remaining_time":5.10879103},
{"learn":[0.4172296237],"iteration":375,"passed_time":3.074787885,"remaining_time":5.102839468},
{"learn":[0.4165713224],"iteration":376,"passed_time":3.088250836,"remaining_time":5.103395944},
{"learn":[0.4163095863],"iteration":377,"passed_time":3.09849069,"remaining_time":5.098574627},
{"learn":[0.416038554],"iteration":378,"passed_time":3.104313688,"remaining_time":5.0864876},
{"learn":[0.4158032967],"iteration":379,"passed_time":3.116083374,"remaining_time":5.084136031},
{"learn":[0.4151153134],"iteration":380,"passed_time":3.122815187,"remaining_time":5.073550133},
{"learn":[0.4147206556],"iteration":381,"passed_time":3.147261097,"remaining_time":5.091642298},
{"learn":[0.4142388536],"iteration":382,"passed_time":3.155959855,"remaining_time":5.084144204},
{"learn":[0.4140759342],"iteration":383,"passed_time":3.163503623,"remaining_time":5.074787062},
{"learn":[0.4136149276],"iteration":384,"passed_time":3.17014139,"remaining_time":5.063992091},
{"learn":[0.413089739],"iteration":385,"passed_time":3.178129136,"remaining_time":5.055366035},
{"learn":[0.4124571549],"iteration":386,"passed_time":3.190001356,"remaining_time":5.052896205},
{"learn":[0.4120325369],"iteration":387,"passed_time":3.19269114,"remaining_time":5.035894272},
{"learn":[0.4115632905],"iteration":388,"passed_time":3.208413641,"remaining_time":5.039436337},
{"learn":[0.4109950154],"iteration":389,"passed_time":3.226370268,"remaining_time":5.046374009},
{"learn":[0.4103912027],"iteration":390,"passed_time":3.230539871,"remaining_time":5.031710438},
{"learn":[0.4098856813],"iteration":391,"passed_time":3.235883573,"remaining_time":5.01892146},
{"learn":[0.4093789558],"iteration":392,"passed_time":3.239507318,"remaining_time":5.003513847},
{"learn":[0.4090193422],"iteration":393,"passed_time":3.253863592,"remaining_time":5.004673443},
{"learn":[0.4088184491],"iteration":394,"passed_time":3.261211107,"remaining_time":4.995019543},
{"learn":[0.4083876571],"iteration":395,"passed_time":3.266457208,"remaining_time":4.982172105},
{"learn":[0.4080610154],"iteration":396,"passed_time":3.272615125,"remaining_time":4.97074791},
{"learn":[0.407391052],"iteration":397,"passed_time":3.279330639,"remaining_time":4.960193579},
{"learn":[0.4068337304],"iteration":398,"passed_time":3.313791028,"remaining_time":4.991449644},
{"learn":[0.4063633796],"iteration":399,"passed_time":3.323886309,"remaining_time":4.985829464},
{"learn":[0.4058726993],"iteration":400,"passed_time":3.327605551,"remaining_time":4.970662656},
{"learn":[0.4050648157],"iteration":401,"passed_time":3.332674949,"remaining_time":4.957561242},
{"learn":[0.4044759285],"iteration":402,"passed_time":3.341027015,"remaining_time":4.9493626},
{"learn":[0.4040254537],"iteration":403,"passed_time":3.348530982,"remaining_time":4.939912043},
{"learn":[0.4038937428],"iteration":404,"passed_time":3.355349198,"remaining_time":4.929463636},
{"learn":[0.4036460966],"iteration":405,"passed_time":3.36351098,"remaining_time":4.920998824},
{"learn":[0.4032470948],"iteration":406,"passed_time":3.372223901,"remaining_time":4.913338509},
{"learn":[0.4026494893],"iteration":407,"passed_time":3.378071527,"remaining_time":4.901515549},
{"learn":[0.4022688838],"iteration":408,"passed_time":3.385527176,"remaining_time":4.892045381},
{"learn":[0.4019324713],"iteration":409,"passed_time":3.390065061,"remaining_time":4.878386308},
{"learn":[0.4015460588],"iteration":410,"passed_time":3.397226978,"remaining_time":4.868532092},
{"learn":[0.4014268048],"iteration":411,"passed_time":3.407084478,"remaining_time":4.862538042},
{"learn":[0.4011670682],"iteration":412,"passed_time":3.443521961,"remaining_time":4.894303611},
{"learn":[0.4006356636],"iteration":413,"passed_time":3.455143802,"remaining_time":4.890614174},
{"learn":[0.3998177013],"iteration":414,"passed_time":3.461014058,"remaining_time":4.878778853},
{"learn":[0.3995361499],"iteration":415,"passed_time":3.470809734,"remaining_time":4.872482896},
{"learn":[0.3992051383],"iteration":416,"passed_time":3.477587523,"remaining_time":4.861950901},
{"learn":[0.3987456588],"iteration":417,"passed_time":3.489865111,"remaining_time":4.859094485},
{"learn":[0.398384501],"iteration":418,"passed_time":3.513769141,"remaining_time":4.872314727},
{"learn":[0.3980971702],"iteration":419,"passed_time":3.532747424,"remaining_time":4.878555967},
{"learn":[0.3979269029],"iteration":420,"passed_time":3.552787507,"remaining_time":4.886137687},
{"learn":[0.3974303333],"iteration":421,"passed_time":3.561254242,"remaining_time":4.877736853},
{"learn":[0.396969697],"iteration":422,"passed_time":3.5751437,"remaining_time":4.87673266},
{"learn":[0.3966073179],"iteration":423,"passed_time":3.59404555,"remaining_time":4.882476974},
{"learn":[0.3962468571],"iteration":424,"passed_time":3.598716187,"remaining_time":4.868851312},
{"learn":[0.3956122227],"iteration":425,"passed_time":3.609523939,"remaining_time":4.86353695},
{"learn":[0.3951060341],"iteration":426,"passed_time":3.614803288,"remaining_time":4.850778183},
{"learn":[0.3945850095],"iteration":427,"passed_time":3.625362325,"remaining_time":4.845110397},
{"learn":[0.3939903908],"iteration":428,"passed_time":3.629099772,"remaining_time":4.830340256},
{"learn":[0.3936709072],"iteration":429,"passed_time":3.642860342,"remaining_time":4.828907895},
{"learn":[0.3932728376],"iteration":430,"passed_time":3.658574126,"remaining_time":4.829996932},
{"learn":[0.393042608],"iteration":431,"passed_time":3.695177337,"remaining_time":4.858473906},
{"learn":[0.3925996544],"iteration":432,"passed_time":3.748948779,"remaining_time":4.909131543},
{"learn":[0.3920309373],"iteration":433,"passed_time":3.753731837,"remaining_time":4.895419861},
{"learn":[0.3915806821],"iteration":434,"passed_time":3.762860339,"remaining_time":4.887393314},
{"learn":[0.3909917347],"iteration":435,"passed_time":3.766767778,"remaining_time":4.872607859},
{"learn":[0.390477633],"iteration":436,"passed_time":3.778803961,"remaining_time":4.868344691},
{"learn":[0.3902846652],"iteration":437,"passed_time":3.783108753,"remaining_time":4.854125843},
{"learn":[0.3899490276],"iteration":438,"passed_time":3.792888531,"remaining_time":4.846948669},
{"learn":[0.3896238108],"iteration":439,"passed_time":3.79783643,"remaining_time":4.833610001},
{"learn":[0.3893042328],"iteration":440,"passed_time":3.802276287,"remaining_time":4.819665407},
{"learn":[0.388927596],"iteration":441,"passed_time":3.81151912,"remaining_time":4.811827306},
{"learn":[0.3888422919],"iteration":442,"passed_time":3.814603981,"remaining_time":4.79624022},
{"learn":[0.3887078823],"iteration":443,"passed_time":3.818355732,"remaining_time":4.781544565},
{"learn":[0.3880981301],"iteration":444,"passed_time":3.824331258,"remaining_time":4.769671569},
{"learn":[0.387916342],"iteration":445,"passed_time":3.835583539,"remaining_time":4.764379552},
{"learn":[0.3875037686],"iteration":446,"passed_time":3.840992087,"remaining_time":4.751831374},
{"learn":[0.3870058225],"iteration":447,"passed_time":3.862379917,"remaining_time":4.759003827},
{"learn":[0.3866706457],"iteration":448,"passed_time":3.873460301,"remaining_time":4.753400057},
{"learn":[0.3864576955],"iteration":449,"passed_time":3.889301826,"remaining_time":4.753591121},
{"learn":[0.3860914658],"iteration":450,"passed_time":3.91346976,"remaining_time":4.763846781},
{"learn":[0.3858767869],"iteration":451,"passed_time":3.929260137,"remaining_time":4.763793263},
{"learn":[0.38534397],"iteration":452,"passed_time":3.936934917,"remaining_time":4.753870639},
{"learn":[0.3849229167],"iteration":453,"passed_time":3.944139889,"remaining_time":4.743392906},
{"learn":[0.3842487799],"iteration":454,"passed_time":3.94955607,"remaining_time":4.730786941},
{"learn":[0.3837828128],"iteration":455,"passed_time":3.954635474,"remaining_time":4.717810741},
{"learn":[0.3833817917],"iteration":456,"passed_time":3.960645901,"remaining_time":4.705975327},
{"learn":[0.3830027823],"iteration":457,"passed_time":3.964696839,"remaining_time":4.691846478},
{"learn":[0.3823662284],"iteration":458,"passed_time":3.968148248,"remaining_time":4.677054907},
{"learn":[0.3819308237],"iteration":459,"passed_time":3.973570161,"remaining_time":4.664625841},
{"learn":[0.3813741384],"iteration":460,"passed_time":3.978708268,"remaining_time":4.65189535},
{"learn":[0.3810110633],"iteration":461,"passed_time":3.982938926,"remaining_time":4.638141001},
{"learn":[0.3806780709],"iteration":462,"passed_time":3.990390137,"remaining_time":4.628163075},
{"learn":[0.3802597412],"iteration":463,"passed_time":3.997555269,"remaining_time":4.617865569},
{"learn":[0.3796086063],"iteration":464,"passed_time":4.004396102,"remaining_time":4.607208418},
{"learn":[0.3790421823],"iteration":465,"passed_time":4.021307893,"remaining_time":4.608108186},
{"learn":[0.3788352338],"iteration":466,"passed_time":4.02543588,"remaining_time":4.594341165},
{"learn":[0.3785123566],"iteration":467,"passed_time":4.028990558,"remaining_time":4.579963625},
{"learn":[0.3780898904],"iteration":468,"passed_time":4.055038007,"remaining_time":4.591098469},
{"learn":[0.3777573683],"iteration":469,"passed_time":4.060686021,"remaining_time":4.579071471},
{"learn":[0.3772905193],"iteration":470,"passed_time":4.068680711,"remaining_time":4.56970721},
{"learn":[0.3766531586],"iteration":471,"passed_time":4.073134424,"remaining_time":4.556387661},
{"learn":[0.3759923644],"iteration":472,"passed_time":4.082064348,"remaining_time":4.548092836},
{"learn":[0.3755133698],"iteration":473,"passed_time":4.086123763,"remaining_time":4.534390505},
{"learn":[0.3750247321],"iteration":474,"passed_time":4.091282992,"remaining_time":4.52194436},
{"learn":[0.3746832328],"iteration":475,"passed_time":4.098865182,"remaining_time":4.512196125},
{"learn":[0.3743352073],"iteration":476,"passed_time":4.105721082,"remaining_time":4.501660641},
{"learn":[0.3739031752],"iteration":477,"passed_time":4.112596353,"remaining_time":4.491161708},
{"learn":[0.3737041371],"iteration":478,"passed_time":4.116244789,"remaining_time":4.477168132},
{"learn":[0.3732391767],"iteration":479,"passed_time":4.121262402,"remaining_time":4.464700935},
{"learn":[0.3730752071],"iteration":480,"passed_time":4.128449803,"remaining_time":4.45460592},
{"learn":[0.3727169313],"iteration":481,"passed_time":4.132256112,"remaining_time":4.440889349},
{"learn":[0.3721778227],"iteration":482,"passed_time":4.138536571,"remaining_time":4.429862127},
{"learn":[0.3716548549],"iteration":483,"passed_time":4.143637229,"remaining_time":4.417596715},
{"learn":[0.3712957628],"iteration":484,"passed_time":4.153267179,"remaining_time":4.410170304},
{"learn":[0.3708710163],"iteration":485,"passed_time":4.156685754,"remaining_time":4.396165592},
{"learn":[0.370512762],"iteration":486,"passed_time":4.160561648,"remaining_time":4.382686089},
{"learn":[0.3701321957],"iteration":487,"passed_time":4.166030257,"remaining_time":4.370916991},
{"learn":[0.369872006],"iteration":488,"passed_time":4.175181895,"remaining_time":4.363022389},
{"learn":[0.3697619041],"iteration":489,"passed_time":4.182009531,"remaining_time":4.352703798},
{"learn":[0.3693610176],"iteration":490,"passed_time":4.188310223,"remaining_time":4.341853164},
{"learn":[0.3690508273],"iteration":491,"passed_time":4.191950736,"remaining_time":4.328274338},
{"learn":[0.3688084213],"iteration":492,"passed_time":4.197554433,"remaining_time":4.316754762},
{"learn":[0.3687029034],"iteration":493,"passed_time":4.203839642,"remaining_time":4.305957204},
{"learn":[0.3684255238],"iteration":494,"passed_time":4.208029263,"remaining_time":4.293039955},
{"learn":[0.3679146618],"iteration":495,"passed_time":4.252042813,"remaining_time":4.320624148},
{"learn":[0.3672854282],"iteration":496,"passed_time":4.255904771,"remaining_time":4.307283903},
{"learn":[0.3668035694],"iteration":497,"passed_time":4.299284607,"remaining_time":4.333817013},
{"learn":[0.3665322049],"iteration":498,"passed_time":4.304920122,"remaining_time":4.322174311},
{"learn":[0.3664103012],"iteration":499,"passed_time":4.308141026,"remaining_time":4.308141026},
{"learn":[0.3658739698],"iteration":500,"passed_time":4.316932453,"remaining_time":4.299699189},
{"learn":[0.3656117524],"iteration":501,"passed_time":4.324345896,"remaining_time":4.289888956},
{"learn":[0.3651661343],"iteration":502,"passed_time":4.349804294,"remaining_time":4.29791796},
{"learn":[0.3649868093],"iteration":503,"passed_time":4.358758833,"remaining_time":4.289572185},
{"learn":[0.3644267972],"iteration":504,"passed_time":4.364390577,"remaining_time":4.277967001},
{"learn":[0.3641508503],"iteration":505,"passed_time":4.373434314,"remaining_time":4.269716505},
{"learn":[0.3639161035],"iteration":506,"passed_time":4.377994726,"remaining_time":4.257103353},
{"learn":[0.363464212],"iteration":507,"passed_time":4.383556658,"remaining_time":4.245491881},
{"learn":[0.3632132759],"iteration":508,"passed_time":4.390098969,"remaining_time":4.234849889},
{"learn":[0.3628097679],"iteration":509,"passed_time":4.397358084,"remaining_time":4.224912669},
{"learn":[0.3625561352],"iteration":510,"passed_time":4.411436249,"remaining_time":4.2215114},
{"learn":[0.3621713525],"iteration":511,"passed_time":4.427431162,"remaining_time":4.219895326},
{"learn":[0.3617480353],"iteration":512,"passed_time":4.432592432,"remaining_time":4.207938625},
{"learn":[0.3613036297],"iteration":513,"passed_time":4.440663798,"remaining_time":4.198759934},
{"learn":[0.3610031472],"iteration":514,"passed_time":4.446454156,"remaining_time":4.187437409},
{"learn":[0.3607274073],"iteration":515,"passed_time":4.455230154,"remaining_time":4.178936812},
{"learn":[0.3603708744],"iteration":516,"passed_time":4.460465848,"remaining_time":4.167127668},
{"learn":[0.3599569174],"iteration":517,"passed_time":4.467033718,"remaining_time":4.156583498},
{"learn":[0.3593508226],"iteration":518,"passed_time":4.474941967,"remaining_time":4.147296891},
{"learn":[0.3590414469],"iteration":519,"passed_time":4.48446714,"remaining_time":4.139508129},
{"learn":[0.3584830491],"iteration":520,"passed_time":4.503870273,"remaining_time":4.140794358},
{"learn":[0.3579875899],"iteration":521,"passed_time":4.51323223,"remaining_time":4.132806525},
{"learn":[0.3577663369],"iteration":522,"passed_time":4.524788448,"remaining_time":4.126814703},
{"learn":[0.3573862463],"iteration":523,"passed_time":4.529395887,"remaining_time":4.114489394},
{"learn":[0.357168005],"iteration":524,"passed_time":4.547847454,"remaining_time":4.114719125},
{"learn":[0.3567394874],"iteration":525,"passed_time":4.559531582,"remaining_time":4.10877941},
{"learn":[0.3564824611],"iteration":526,"passed_time":4.581005867,"remaining_time":4.111604886},
{"learn":[0.3561114067],"iteration":527,"passed_time":4.616153937,"remaining_time":4.126561853},
{"learn":[0.3555498791],"iteration":528,"passed_time":4.624345083,"remaining_time":4.117328042},
{"learn":[0.3552680468],"iteration":529,"passed_time":4.630875283,"remaining_time":4.106625251},
{"learn":[0.3549321586],"iteration":530,"passed_time":4.644494538,"remaining_time":4.102199507},
{"learn":[0.3544072161],"iteration":531,"passed_time":4.652742185,"remaining_time":4.093013802},
{"learn":[0.3540469287],"iteration":532,"passed_time":4.657059007,"remaining_time":4.080387535},
{"learn":[0.3536599841],"iteration":533,"passed_time":4.663921012,"remaining_time":4.070013468},
{"learn":[0.35325589],"iteration":534,"passed_time":4.669566515,"remaining_time":4.058595195},
{"learn":[0.3528770644],"iteration":535,"passed_time":4.675980313,"remaining_time":4.047863555},
{"learn":[0.3523528708],"iteration":536,"passed_time":4.684299098,"remaining_time":4.03879047},
{"learn":[0.3522414637],"iteration":537,"passed_time":4.688574012,"remaining_time":4.026247571},
{"learn":[0.351792463],"iteration":538,"passed_time":4.695340094,"remaining_time":4.015866018},
{"learn":[0.3515710588],"iteration":539,"passed_time":4.702173152,"remaining_time":4.005554907},
{"learn":[0.3511815126],"iteration":540,"passed_time":4.710356924,"remaining_time":3.99640264},
{"learn":[0.3507853139],"iteration":541,"passed_time":4.72875546,"remaining_time":3.99588561},
{"learn":[0.3504590111],"iteration":542,"passed_time":4.747213617,"remaining_time":3.995352897},
{"learn":[0.3500456081],"iteration":543,"passed_time":4.756967986,"remaining_time":3.987458459},
{"learn":[0.3499551686],"iteration":544,"passed_time":4.766116421,"remaining_time":3.979051324},
{"learn":[0.3494542064],"iteration":545,"passed_time":4.785121598,"remaining_time":3.978837373},
{"learn":[0.349165508],"iteration":546,"passed_time":4.797567567,"remaining_time":3.973122684},
{"learn":[0.3487082091],"iteration":547,"passed_time":4.807590309,"remaining_time":3.965384708},
{"learn":[0.348341811],"iteration":548,"passed_time":4.814589781,"remaining_time":3.955154811},
{"learn":[0.347973068],"iteration":549,"passed_time":4.819090538,"remaining_time":3.942892259},
{"learn":[0.3477126029],"iteration":550,"passed_time":4.826923851,"remaining_time":3.93337352},
{"learn":[0.3473388481],"iteration":551,"passed_time":4.835366429,"remaining_time":3.924355363},
{"learn":[0.3469719837],"iteration":552,"passed_time":4.851992184,"remaining_time":3.921953899},
{"learn":[0.3467595721],"iteration":553,"passed_time":4.864072558,"remaining_time":3.915841807},
{"learn":[0.3463687328],"iteration":554,"passed_time":4.880969842,"remaining_time":3.913570414},
{"learn":[0.3460070016],"iteration":555,"passed_time":4.889378768,"remaining_time":3.904467937},
{"learn":[0.3457018689],"iteration":556,"passed_time":4.898049205,"remaining_time":3.895575939},
{"learn":[0.3455768857],"iteration":557,"passed_time":4.901637283,"remaining_time":3.882658923},
{"learn":[0.3449395111],"iteration":558,"passed_time":4.9101568,"remaining_time":3.87366574},
{"learn":[0.3447925724],"iteration":559,"passed_time":4.915499677,"remaining_time":3.862178318},
{"learn":[0.3445285079],"iteration":560,"passed_time":4.920757732,"remaining_time":3.850646425},
{"learn":[0.3442774095],"iteration":561,"passed_time":4.926520294,"remaining_time":3.839530052},
{"learn":[0.3439542613],"iteration":562,"passed_time":4.934167485,"remaining_time":3.829895544},
{"learn":[0.3434778303],"iteration":563,"passed_time":4.941088183,"remaining_time":3.819706467},
{"learn":[0.3431406435],"iteration":564,"passed_time":4.950494608,"remaining_time":3.811442751},
{"learn":[0.3429196604],"iteration":565,"passed_time":4.956568616,"remaining_time":3.800619751},
{"learn":[0.3426711592],"iteration":566,"passed_time":4.960438861,"remaining_time":3.788130559},
{"learn":[0.342426177],"iteration":567,"passed_time":4.967975697,"remaining_time":3.77846039},
{"learn":[0.3422140705],"iteration":568,"passed_time":4.973296153,"remaining_time":3.767118879},
{"learn":[0.341719996],"iteration":569,"passed_time":4.979895995,"remaining_time":3.756763646},
{"learn":[0.3415122137],"iteration":570,"passed_time":4.994787291,"remaining_time":3.752651047},
{"learn":[0.3410592361],"iteration":571,"passed_time":5.003361597,"remaining_time":3.743774062},
{"learn":[0.3407225272],"iteration":572,"passed_time":5.016422268,"remaining_time":3.738241376},
{"learn":[0.3404332642],"iteration":573,"passed_time":5.021998234,"remaining_time":3.727127609},
{"learn":[0.3401460808],"iteration":574,"passed_time":5.027140699,"remaining_time":3.71571269},
{"learn":[0.3398233271],"iteration":575,"passed_time":5.034450093,"remaining_time":3.705914652},
{"learn":[0.3393418552],"iteration":576,"passed_time":5.039918441,"remaining_time":3.694775564},
{"learn":[0.3388819032],"iteration":577,"passed_time":5.048417628,"remaining_time":3.685868926},
{"learn":[0.338460441],"iteration":578,"passed_time":5.14347907,"remaining_time":3.73990447},
{"learn":[0.3380629641],"iteration":579,"passed_time":5.150561727,"remaining_time":3.729717113},
{"learn":[0.3376528339],"iteration":580,"passed_time":5.160896084,"remaining_time":3.721885472},
{"learn":[0.3373325765],"iteration":581,"passed_time":5.165484684,"remaining_time":3.709918553},
{"learn":[0.3370144566],"iteration":582,"passed_time":5.213996293,"remaining_time":3.729393575},
{"learn":[0.3366062906],"iteration":583,"passed_time":5.222247416,"remaining_time":3.719957064},
{"learn":[0.3364300386],"iteration":584,"passed_time":5.227305263,"remaining_time":3.708259289},
{"learn":[0.3363167097],"iteration":585,"passed_time":5.245961611,"remaining_time":3.706191309},
{"learn":[0.3360426056],"iteration":586,"passed_time":5.265223226,"remaining_time":3.704492662},
{"learn":[0.3357733367],"iteration":587,"passed_time":5.273250569,"remaining_time":3.694862644},
{"learn":[0.3353271368],"iteration":588,"passed_time":5.281541712,"remaining_time":3.685422145},
{"learn":[0.3350485078],"iteration":589,"passed_time":5.290322003,"remaining_time":3.67632546},
{"learn":[0.334774168],"iteration":590,"passed_time":5.29513136,"remaining_time":3.66448177},
{"learn":[0.3344954401],"iteration":591,"passed_time":5.304878329,"remaining_time":3.656064794},
{"learn":[0.3343418826],"iteration":592,"passed_time":5.315141785,"remaining_time":3.647997819},
{"learn":[0.3339844567],"iteration":593,"passed_time":5.320718459,"remaining_time":3.636720024},
{"learn":[0.3338279432],"iteration":594,"passed_time":5.334794169,"remaining_time":3.631246451},
{"learn":[0.3335045466],"iteration":595,"passed_time":5.347866064,"remaining_time":3.625063573},
{"learn":[0.3331329006],"iteration":596,"passed_time":5.35282582,"remaining_time":3.613381584},
{"learn":[0.3329852836],"iteration":597,"passed_time":5.360313004,"remaining_time":3.603421116},
{"learn":[0.332720964],"iteration":598,"passed_time":5.368561627,"remaining_time":3.593978652},
{"learn":[0.3323642766],"iteration":599,"passed_time":5.372931196,"remaining_time":3.581954131},
{"learn":[0.3320533219],"iteration":600,"passed_time":5.379741806,"remaining_time":3.571575675},
{"learn":[0.3317069549],"iteration":601,"passed_time":5.386290853,"remaining_time":3.561036145},
{"learn":[0.3312487575],"iteration":602,"passed_time":5.390410296,"remaining_time":3.548910261},
{"learn":[0.3308891179],"iteration":603,"passed_time":5.396313553,"remaining_time":3.537980409},
{"learn":[0.3303668361],"iteration":604,"passed_time":5.400915346,"remaining_time":3.526217457},
{"learn":[0.3302281173],"iteration":605,"passed_time":5.404352729,"remaining_time":3.513721082},
{"learn":[0.3299795985],"iteration":606,"passed_time":5.415427536,"remaining_time":3.506199376},
{"learn":[0.3297259636],"iteration":607,"passed_time":5.449059016,"remaining_time":3.513209103},
{"learn":[0.3295713569],"iteration":608,"passed_time":5.46913079,"remaining_time":3.511379538},
{"learn":[0.3292901417],"iteration":609,"passed_time":5.480013549,"remaining_time":3.50361522},
{"learn":[0.3289072282],"iteration":610,"passed_time":5.500185436,"remaining_time":3.501754721},
{"learn":[0.3285713577],"iteration":611,"passed_time":5.506519122,"remaining_time":3.491061143},
{"learn":[0.3281384155],"iteration":612,"passed_time":5.518349626,"remaining_time":3.483852048},
{"learn":[0.3280060446],"iteration":613,"passed_time":5.540346629,"remaining_time":3.483019216},
{"learn":[0.3275051696],"iteration":614,"passed_time":5.551498528,"remaining_time":3.475328347},
{"learn":[0.3270147509],"iteration":615,"passed_time":5.567375363,"remaining_time":3.470571655},
{"learn":[0.3268906756],"iteration":616,"passed_time":5.573572299,"remaining_time":3.459770163},
{"learn":[0.3265596672],"iteration":617,"passed_time":5.577746103,"remaining_time":3.447733028},
{"learn":[0.3262741295],"iteration":618,"passed_time":5.606368091,"remaining_time":3.450769374},
{"learn":[0.3259380134],"iteration":619,"passed_time":5.61138871,"remaining_time":3.439238242},
{"learn":[0.3257176208],"iteration":620,"passed_time":5.617117658,"remaining_time":3.428160374},
{"learn":[0.3252501637],"iteration":621,"passed_time":5.62312387,"remaining_time":3.417268204},
{"learn":[0.3248770888],"iteration":622,"passed_time":5.631557865,"remaining_time":3.407860859},
{"learn":[0.3245060709],"iteration":623,"passed_time":5.648147953,"remaining_time":3.403371202},
{"learn":[0.3241377368],"iteration":624,"passed_time":5.658465401,"remaining_time":3.395079241},
{"learn":[0.3240061253],"iteration":625,"passed_time":5.666070916,"remaining_time":3.385160579},
{"learn":[0.3237004032],"iteration":626,"passed_time":5.672127205,"remaining_time":3.374327668},
{"learn":[0.3233517635],"iteration":627,"passed_time":5.688066438,"remaining_time":3.369364196},
{"learn":[0.3231467798],"iteration":628,"passed_time":5.696001863,"remaining_time":3.359644978},
{"learn":[0.3228572762],"iteration":629,"passed_time":5.709613663,"remaining_time":3.353265167},
{"learn":[0.3226427348],"iteration":630,"passed_time":5.71425115,"remaining_time":3.341614381},
{"learn":[0.3223115967],"iteration":631,"passed_time":5.724167844,"remaining_time":3.333059757},
{"learn":[0.3219576489],"iteration":632,"passed_time":5.730870876,"remaining_time":3.322637617},
{"learn":[0.321758964],"iteration":633,"passed_time":5.736498109,"remaining_time":3.311606164},
{"learn":[0.3215642886],"iteration":634,"passed_time":5.764013637,"remaining_time":3.313173193},
{"learn":[0.3213011313],"iteration":635,"passed_time":5.768632642,"remaining_time":3.301544468},
{"learn":[0.3210149645],"iteration":636,"passed_time":5.775501958,"remaining_time":3.291220111},
{"learn":[0.320735199],"iteration":637,"passed_time":5.785724525,"remaining_time":3.282809213},
{"learn":[0.3203544291],"iteration":638,"passed_time":5.789574525,"remaining_time":3.270792494},
{"learn":[0.3199569831],"iteration":639,"passed_time":5.794780512,"remaining_time":3.259564038},
{"learn":[0.31975828],"iteration":640,"passed_time":5.807777984,"remaining_time":3.252718091},
{"learn":[0.319649709],"iteration":641,"passed_time":5.826915206,"remaining_time":3.249276704},
{"learn":[0.3193829126],"iteration":642,"passed_time":5.851698624,"remaining_time":3.24892132},
{"learn":[0.3193214171],"iteration":643,"passed_time":5.858469515,"remaining_time":3.238532837},
{"learn":[0.3189410026],"iteration":644,"passed_time":5.872267094,"remaining_time":3.232022974},
{"learn":[0.3186595258],"iteration":645,"passed_time":5.888743705,"remaining_time":3.226958624},
{"learn":[0.3185681033],"iteration":646,"passed_time":5.893191098,"remaining_time":3.215295916},
{"learn":[0.3182552948],"iteration":647,"passed_time":5.899286494,"remaining_time":3.204550688},
{"learn":[0.3178482895],"iteration":648,"passed_time":5.907546589,"remaining_time":3.194990528},
{"learn":[0.3175886191],"iteration":649,"passed_time":5.913183588,"remaining_time":3.184021932},
{"learn":[0.3174373811],"iteration":650,"passed_time":5.91977688,"remaining_time":3.173582382},
{"learn":[0.3170405108],"iteration":651,"passed_time":5.926723055,"remaining_time":3.16334298},
{"learn":[0.3166118237],"iteration":652,"passed_time":5.935143625,"remaining_time":3.153897149},
{"learn":[0.3162352233],"iteration":653,"passed_time":5.940642181,"remaining_time":3.142908554},
{"learn":[0.3160330791],"iteration":654,"passed_time":5.946050245,"remaining_time":3.13188906},
{"learn":[0.3158140492],"iteration":655,"passed_time":5.951746886,"remaining_time":3.121038001},
{"learn":[0.3152958585],"iteration":656,"passed_time":5.957544399,"remaining_time":3.110255295},
{"learn":[0.3150341555],"iteration":657,"passed_time":5.964567319,"remaining_time":3.100124655},
{"learn":[0.3147899321],"iteration":658,"passed_time":5.970658048,"remaining_time":3.089521084},
{"learn":[0.3144945221],"iteration":659,"passed_time":5.97903911,"remaining_time":3.080111057},
{"learn":[0.3141565924],"iteration":660,"passed_time":6.012616257,"remaining_time":3.083626189},
{"learn":[0.3138262674],"iteration":661,"passed_time":6.01917537,"remaining_time":3.073234555},
{"learn":[0.3134144423],"iteration":662,"passed_time":6.027699907,"remaining_time":3.063853497},
{"learn":[0.3131553476],"iteration":663,"passed_time":6.040504537,"remaining_time":3.05664085},
{"learn":[0.3127188252],"iteration":664,"passed_time":6.044661848,"remaining_time":3.045055217},
{"learn":[0.3126027694],"iteration":665,"passed_time":6.054268142,"remaining_time":3.036224564},
{"learn":[0.3122890376],"iteration":666,"passed_time":6.060027225,"remaining_time":3.025470863},
{"learn":[0.3121625213],"iteration":667,"passed_time":6.070682735,"remaining_time":3.01716567},
{"learn":[0.3119533658],"iteration":668,"passed_time":6.077168338,"remaining_time":3.006790314},
{"learn":[0.3116310206],"iteration":669,"passed_time":6.08539236,"remaining_time":2.997282804},
{"learn":[0.3114098758],"iteration":670,"passed_time":6.091978786,"remaining_time":2.986976186},
{"learn":[0.3112065914],"iteration":671,"passed_time":6.102339325,"remaining_time":2.978522766},
{"learn":[0.3108299833],"iteration":672,"passed_time":6.111046907,"remaining_time":2.969260533},
{"learn":[0.310614741],"iteration":673,"passed_time":6.117302614,"remaining_time":2.958814024},
{"learn":[0.3105451636],"iteration":674,"passed_time":6.122187697,"remaining_time":2.947720002},
{"learn":[0.3102518497],"iteration":675,"passed_time":6.128769514,"remaining_time":2.937457578},
{"learn":[0.3099220478],"iteration":676,"passed_time":6.135037235,"remaining_time":2.92705617},
{"learn":[0.3095350718],"iteration":677,"passed_time":6.147832687,"remaining_time":2.919767146},
{"learn":[0.3093653531],"iteration":678,"passed_time":6.159909054,"remaining_time":2.912121953},
{"learn":[0.3091340644],"iteration":679,"passed_time":6.165462639,"remaining_time":2.901394183},
{"learn":[0.3089473584],"iteration":680,"passed_time":6.175947551,"remaining_time":2.892991584},
{"learn":[0.3086701869],"iteration":681,"passed_time":6.187079321,"remaining_time":2.884884493},
{"learn":[0.3085849296],"iteration":682,"passed_time":6.192396844,"remaining_time":2.874069984},
{"learn":[0.3083196338],"iteration":683,"passed_time":6.199203586,"remaining_time":2.863959551},
{"learn":[0.3080608944],"iteration":684,"passed_time":6.204402957,"remaining_time":2.853119608},
{"learn":[0.3076149943],"iteration":685,"passed_time":6.220192552,"remaining_time":2.84714353},
{"learn":[0.3073634091],"iteration":686,"passed_time":6.228908631,"remaining_time":2.837916159},
{"learn":[0.3071637882],"iteration":687,"passed_time":6.240396732,"remaining_time":2.829947355},
{"learn":[0.3069617356],"iteration":688,"passed_time":6.270329693,"remaining_time":2.830293954},
{"learn":[0.3067588503],"iteration":689,"passed_time":6.280847412,"remaining_time":2.821829997},
{"learn":[0.3064532589],"iteration":690,"passed_time":6.287432095,"remaining_time":2.811601327},
{"learn":[0.3060854381],"iteration":691,"passed_time":6.296113536,"remaining_time":2.802316429},
{"learn":[0.3059627033],"iteration":692,"passed_time":6.302706372,"remaining_time":2.792108018},
{"learn":[0.3056613223],"iteration":693,"passed_time":6.310584783,"remaining_time":2.782476864},
{"learn":[0.3053737978],"iteration":694,"passed_time":6.319944762,"remaining_time":2.773500939},
{"learn":[0.3052318378],"iteration":695,"passed_time":6.325253993,"remaining_time":2.762754617},
{"learn":[0.3048546044],"iteration":696,"passed_time":6.336522542,"remaining_time":2.754614534},
{"learn":[0.3046695546],"iteration":697,"passed_time":6.349680265,"remaining_time":2.747282865},
{"learn":[0.304185832],"iteration":698,"passed_time":6.359250407,"remaining_time":2.73838966},
{"learn":[0.3039769006],"iteration":699,"passed_time":6.37190622,"remaining_time":2.730816952},
{"learn":[0.3036169172],"iteration":700,"passed_time":6.377574401,"remaining_time":2.720249281},
{"learn":[0.3033083683],"iteration":701,"passed_time":6.387734531,"remaining_time":2.711602408},
{"learn":[0.3030941619],"iteration":702,"passed_time":6.392238182,"remaining_time":2.700561508},
{"learn":[0.3027614294],"iteration":703,"passed_time":6.399835852,"remaining_time":2.690840074},
{"learn":[0.3025555644],"iteration":704,"passed_time":6.411937268,"remaining_time":2.683009211},
{"learn":[0.3024869037],"iteration":705,"passed_time":6.416660464,"remaining_time":2.672093734},
{"learn":[0.3021183726],"iteration":706,"passed_time":6.422490944,"remaining_time":2.661654663},
{"learn":[0.3017161008],"iteration":707,"passed_time":6.428703303,"remaining_time":2.651386108},
{"learn":[0.3014853718],"iteration":708,"passed_time":6.433702089,"remaining_time":2.6406309},
{"learn":[0.3013078372],"iteration":709,"passed_time":6.436904257,"remaining_time":2.629158077},
{"learn":[0.3011071621],"iteration":710,"passed_time":6.441326834,"remaining_time":2.618204578},
{"learn":[0.3008714666],"iteration":711,"passed_time":6.447734292,"remaining_time":2.608072298},
{"learn":[0.3006637091],"iteration":712,"passed_time":6.451830579,"remaining_time":2.597020163},
{"learn":[0.3003181274],"iteration":713,"passed_time":6.455852854,"remaining_time":2.585957866},
{"learn":[0.2999192956],"iteration":714,"passed_time":6.468825345,"remaining_time":2.57848283},
{"learn":[0.2995030174],"iteration":715,"passed_time":6.481804318,"remaining_time":2.570995009},
{"learn":[0.2991208633],"iteration":716,"passed_time":6.494888405,"remaining_time":2.563533359},
{"learn":[0.2986458446],"iteration":717,"passed_time":6.499689769,"remaining_time":2.552802945},
{"learn":[0.298465524],"iteration":718,"passed_time":6.511988491,"remaining_time":2.545019146},
{"learn":[0.2983549166],"iteration":719,"passed_time":6.525214429,"remaining_time":2.537583389},
{"learn":[0.2981044545],"iteration":720,"passed_time":6.530781421,"remaining_time":2.527167845},
{"learn":[0.297934998],"iteration":721,"passed_time":6.540855673,"remaining_time":2.518501215},
{"learn":[0.2975967068],"iteration":722,"passed_time":6.55807481,"remaining_time":2.512568081},
{"learn":[0.2972694674],"iteration":723,"passed_time":6.56515413,"remaining_time":2.502738315},
{"learn":[0.2969758168],"iteration":724,"passed_time":6.575543456,"remaining_time":2.494171656},
{"learn":[0.2967158661],"iteration":725,"passed_time":6.581231164,"remaining_time":2.483825536},
{"learn":[0.296450483],"iteration":726,"passed_time":6.600793046,"remaining_time":2.478702203},
{"learn":[0.2961501242],"iteration":727,"passed_time":6.609256659,"remaining_time":2.469392598},
{"learn":[0.2958212136],"iteration":728,"passed_time":6.619748293,"remaining_time":2.460839215},
{"learn":[0.2953243846],"iteration":729,"passed_time":6.626792133,"remaining_time":2.451005309},
{"learn":[0.295036498],"iteration":730,"passed_time":6.636425457,"remaining_time":2.44213194},
{"learn":[0.294709885],"iteration":731,"passed_time":6.640300034,"remaining_time":2.4311481},
{"learn":[0.2943850193],"iteration":732,"passed_time":6.680841983,"remaining_time":2.433539986},
{"learn":[0.2942550403],"iteration":733,"passed_time":6.685129757,"remaining_time":2.422676451},
{"learn":[0.2941707985],"iteration":734,"passed_time":6.699076989,"remaining_time":2.415313472},
{"learn":[0.2939952055],"iteration":735,"passed_time":6.712274976,"remaining_time":2.40766385},
{"learn":[0.2936165013],"iteration":736,"passed_time":6.719287974,"remaining_time":2.397792045},
{"learn":[0.2932387629],"iteration":737,"passed_time":6.748480871,"remaining_time":2.395802152},
{"learn":[0.2929953811],"iteration":738,"passed_time":6.753799606,"remaining_time":2.385306762},
{"learn":[0.2926721225],"iteration":739,"passed_time":6.764060591,"remaining_time":2.376561829},
{"learn":[0.2923724844],"iteration":740,"passed_time":6.775806444,"remaining_time":2.368331807},
{"learn":[0.2922042901],"iteration":741,"passed_time":6.78176603,"remaining_time":2.358080372},
{"learn":[0.291870716],"iteration":742,"passed_time":6.815178576,"remaining_time":2.357336331},
{"learn":[0.2917745864],"iteration":743,"passed_time":6.821048832,"remaining_time":2.347027555},
{"learn":[0.2916279104],"iteration":744,"passed_time":6.825796186,"remaining_time":2.336346346},
{"learn":[0.2914440146],"iteration":745,"passed_time":6.831255394,"remaining_time":2.325923418},
{"learn":[0.2911295057],"iteration":746,"passed_time":6.841677321,"remaining_time":2.317194595},
{"learn":[0.2908653644],"iteration":747,"passed_time":6.849671731,"remaining_time":2.307643417},
{"learn":[0.2905795867],"iteration":748,"passed_time":6.858878876,"remaining_time":2.298502801},
{"learn":[0.2903681734],"iteration":749,"passed_time":6.870178937,"remaining_time":2.290059646},
{"learn":[0.2899861877],"iteration":750,"passed_time":6.878462918,"remaining_time":2.280608877},
{"learn":[0.2897359387],"iteration":751,"passed_time":6.888836721,"remaining_time":2.271850408},
{"learn":[0.2892817088],"iteration":752,"passed_time":6.894643947,"remaining_time":2.261589714},
{"learn":[0.2890584243],"iteration":753,"passed_time":6.910438498,"remaining_time":2.254599298},
{"learn":[0.2888754711],"iteration":754,"passed_time":6.91700181,"remaining_time":2.244589991},
{"learn":[0.2886252061],"iteration":755,"passed_time":6.933711869,"remaining_time":2.237864677},
{"learn":[0.2883836627],"iteration":756,"passed_time":6.944725232,"remaining_time":2.229284322},
{"learn":[0.2881141051],"iteration":757,"passed_time":6.982999644,"remaining_time":2.229400942},
{"learn":[0.2878960857],"iteration":758,"passed_time":6.992712302,"remaining_time":2.220347384},
{"learn":[0.2877691526],"iteration":759,"passed_time":6.999697552,"remaining_time":2.210430806},
{"learn":[0.2873931505],"iteration":760,"passed_time":7.043960795,"remaining_time":2.212229474},
{"learn":[0.2869711927],"iteration":761,"passed_time":7.057602158,"remaining_time":2.204342931},
{"learn":[0.2869018046],"iteration":762,"passed_time":7.062521768,"remaining_time":2.193732187},
{"learn":[0.2866738483],"iteration":763,"passed_time":7.073790767,"remaining_time":2.185097671},
{"learn":[0.2864460802],"iteration":764,"passed_time":7.080240209,"remaining_time":2.174975751},
{"learn":[0.2860355305],"iteration":765,"passed_time":7.096094309,"remaining_time":2.167736382},
{"learn":[0.2857076586],"iteration":766,"passed_time":7.107144915,"remaining_time":2.159015339},
{"learn":[0.2854932376],"iteration":767,"passed_time":7.113507166,"remaining_time":2.148871956},
{"learn":[0.2851204353],"iteration":768,"passed_time":7.121327303,"remaining_time":2.139176342},
{"learn":[0.2848393729],"iteration":769,"passed_time":7.127316705,"remaining_time":2.128938756},
{"learn":[0.2845897995],"iteration":770,"passed_time":7.133351559,"remaining_time":2.11872569},
{"learn":[0.2842623663],"iteration":771,"passed_time":7.140756234,"remaining_time":2.108928007},
{"learn":[0.2839834696],"iteration":772,"passed_time":7.145999722,"remaining_time":2.098501859},
{"learn":[0.2836509501],"iteration":773,"passed_time":7.154880604,"remaining_time":2.089151184},
{"learn":[0.2832678744],"iteration":774,"passed_time":7.161282642,"remaining_time":2.079082057},
{"learn":[0.2829929684],"iteration":775,"passed_time":7.169478804,"remaining_time":2.069540273},
{"learn":[0.282616761],"iteration":776,"passed_time":7.18252854,"remaining_time":2.061394935},
{"learn":[0.2823947331],"iteration":777,"passed_time":7.188221041,"remaining_time":2.051137623},
{"learn":[0.2820683718],"iteration":778,"passed_time":7.194733026,"remaining_time":2.041124517},
{"learn":[0.2817574298],"iteration":779,"passed_time":7.201954412,"remaining_time":2.031320475},
{"learn":[0.2814593718],"iteration":780,"passed_time":7.209249055,"remaining_time":2.021543589},
{"learn":[0.2812733843],"iteration":781,"passed_time":7.212789893,"remaining_time":2.010726594},
{"learn":[0.2809668537],"iteration":782,"passed_time":7.220810952,"remaining_time":2.00116983},
{"learn":[0.2808775267],"iteration":783,"passed_time":7.225581391,"remaining_time":1.990721404},
{"learn":[0.2806644793],"iteration":784,"passed_time":7.236364024,"remaining_time":1.981934096},
{"learn":[0.280251684],"iteration":785,"passed_time":7.24289599,"remaining_time":1.971984404},
{"learn":[0.2798183875],"iteration":786,"passed_time":7.250440371,"remaining_time":1.962317407},
{"learn":[0.2795956422],"iteration":787,"passed_time":7.256290144,"remaining_time":1.952199887},
{"learn":[0.2793524486],"iteration":788,"passed_time":7.267140776,"remaining_time":1.94343055},
{"learn":[0.279164221],"iteration":789,"passed_time":7.273333333,"remaining_time":1.933417721},
{"learn":[0.2788037509],"iteration":790,"passed_time":7.284283092,"remaining_time":1.924671512},
{"learn":[0.2785382641],"iteration":791,"passed_time":7.295023183,"remaining_time":1.915864674},
{"learn":[0.2780944015],"iteration":792,"passed_time":7.31735636,"remaining_time":1.910079151},
{"learn":[0.2778985329],"iteration":793,"passed_time":7.325542553,"remaining_time":1.900581569},
{"learn":[0.2775288368],"iteration":794,"passed_time":7.342411902,"remaining_time":1.893326339},
{"learn":[0.2773906611],"iteration":795,"passed_time":7.358159627,"remaining_time":1.885759502},
{"learn":[0.2772060456],"iteration":796,"passed_time":7.373790917,"remaining_time":1.878142479},
{"learn":[0.2769497981],"iteration":797,"passed_time":7.392544185,"remaining_time":1.871295646},
{"learn":[0.2766716028],"iteration":798,"passed_time":7.398896402,"remaining_time":1.861299345},
{"learn":[0.2764737468],"iteration":799,"passed_time":7.405490257,"remaining_time":1.851372564},
{"learn":[0.2761551936],"iteration":800,"passed_time":7.412251462,"remaining_time":1.841495681},
{"learn":[0.2759847382],"iteration":801,"passed_time":7.420288681,"remaining_time":1.831941594},
{"learn":[0.2758583614],"iteration":802,"passed_time":7.42597037,"remaining_time":1.821813403},
{"learn":[0.2756710798],"iteration":803,"passed_time":7.44645853,"remaining_time":1.815305811},
{"learn":[0.2754323449],"iteration":804,"passed_time":7.452948468,"remaining_time":1.80537261},
{"learn":[0.2750710387],"iteration":805,"passed_time":7.459428967,"remaining_time":1.795445682},
{"learn":[0.2748812001],"iteration":806,"passed_time":7.465287483,"remaining_time":1.785378543},
{"learn":[0.2747217003],"iteration":807,"passed_time":7.497381598,"remaining_time":1.781556023},
{"learn":[0.2745458324],"iteration":808,"passed_time":7.502662797,"remaining_time":1.771333244},
{"learn":[0.2743302418],"iteration":809,"passed_time":7.511958212,"remaining_time":1.762064272},
{"learn":[0.2741596185],"iteration":810,"passed_time":7.517781892,"remaining_time":1.751986162},
{"learn":[0.2740739082],"iteration":811,"passed_time":7.53792654,"remaining_time":1.745234224},
{"learn":[0.2737854554],"iteration":812,"passed_time":7.548457704,"remaining_time":1.736238119},
{"learn":[0.2736120986],"iteration":813,"passed_time":7.559350314,"remaining_time":1.727320833},
{"learn":[0.273448193],"iteration":814,"passed_time":7.609799139,"remaining_time":1.727377719},
{"learn":[0.2732890922],"iteration":815,"passed_time":7.614092218,"remaining_time":1.716903147},
{"learn":[0.2730071214],"iteration":816,"passed_time":7.62519003,"remaining_time":1.707967902},
{"learn":[0.2729693778],"iteration":817,"passed_time":7.630735265,"remaining_time":1.697791954},
{"learn":[0.2727209539],"iteration":818,"passed_time":7.637607181,"remaining_time":1.687920512},
{"learn":[0.2723873407],"iteration":819,"passed_time":7.642532458,"remaining_time":1.677629076},
{"learn":[0.2720431382],"iteration":820,"passed_time":7.647634945,"remaining_time":1.667389349},
{"learn":[0.2719619329],"iteration":821,"passed_time":7.661990382,"remaining_time":1.6591658},
{"learn":[0.2717445079],"iteration":822,"passed_time":7.671218438,"remaining_time":1.649824622},
{"learn":[0.2716840903],"iteration":823,"passed_time":7.680077731,"remaining_time":1.640404952},
{"learn":[0.2714672105],"iteration":824,"passed_time":7.690628994,"remaining_time":1.631345544},
{"learn":[0.2712009533],"iteration":825,"passed_time":7.695538567,"remaining_time":1.621094081},
{"learn":[0.2709206282],"iteration":826,"passed_time":7.702940465,"remaining_time":1.611376905},
{"learn":[0.2708572342],"iteration":827,"passed_time":7.709464006,"remaining_time":1.601482861},
{"learn":[0.2705836975],"iteration":828,"passed_time":7.717770471,"remaining_time":1.591964717},
{"learn":[0.2703967177],"iteration":829,"passed_time":7.737111007,"remaining_time":1.584709483},
{"learn":[0.2701400088],"iteration":830,"passed_time":7.768690159,"remaining_time":1.579914124},
{"learn":[0.2697468339],"iteration":831,"passed_time":7.786644242,"remaining_time":1.572303164},
{"learn":[0.2694023472],"iteration":832,"passed_time":7.793573242,"remaining_time":1.56245706},
{"learn":[0.2693367595],"iteration":833,"passed_time":7.798712618,"remaining_time":1.552261744},
{"learn":[0.2690867649],"iteration":834,"passed_time":7.807183756,"remaining_time":1.54273691},
{"learn":[0.2687313562],"iteration":835,"passed_time":7.815726773,"remaining_time":1.533228697},
{"learn":[0.2684973589],"iteration":836,"passed_time":7.820470155,"remaining_time":1.522982838},
{"learn":[0.2680952891],"iteration":837,"passed_time":7.823580463,"remaining_time":1.512434409},
{"learn":[0.2680882469],"iteration":838,"passed_time":7.826132682,"remaining_time":1.501796617},
{"learn":[0.2680234136],"iteration":839,"passed_time":7.830539981,"remaining_time":1.491531425},
{"learn":[0.267722036],"iteration":840,"passed_time":7.834292284,"remaining_time":1.48115633},
{"learn":[0.2674735299],"iteration":841,"passed_time":7.838848296,"remaining_time":1.47094778},
{"learn":[0.2674341737],"iteration":842,"passed_time":7.844313595,"remaining_time":1.460921986},
{"learn":[0.2674200794],"iteration":843,"passed_time":7.847537217,"remaining_time":1.450492661},
{"learn":[0.2673562009],"iteration":844,"passed_time":7.851100935,"remaining_time":1.440142775},
{"learn":[0.2671349816],"iteration":845,"passed_time":7.864198694,"remaining_time":1.431544443},
{"learn":[0.2667981259],"iteration":846,"passed_time":7.870739603,"remaining_time":1.421751074},
{"learn":[0.266597931],"iteration":847,"passed_time":7.876117937,"remaining_time":1.411756989},
{"learn":[0.2661300489],"iteration":848,"passed_time":7.885991238,"remaining_time":1.402573235},
{"learn":[0.2659189944],"iteration":849,"passed_time":7.894616732,"remaining_time":1.393167659},
{"learn":[0.265457373],"iteration":850,"passed_time":7.900287926,"remaining_time":1.383246652},
{"learn":[0.2651844245],"iteration":851,"passed_time":7.906437796,"remaining_time":1.373418772},
{"learn":[0.2649715162],"iteration":852,"passed_time":7.910442271,"remaining_time":1.363229793},
{"learn":[0.2647840778],"iteration":853,"passed_time":7.915033242,"remaining_time":1.353155566},
{"learn":[0.2643773318],"iteration":854,"passed_time":7.919077718,"remaining_time":1.343001484},
{"learn":[0.2639130553],"iteration":855,"passed_time":7.924967207,"remaining_time":1.333172054},
{"learn":[0.2635675426],"iteration":856,"passed_time":7.929119666,"remaining_time":1.323061975},
{"learn":[0.2634154183],"iteration":857,"passed_time":7.938550208,"remaining_time":1.313839312},
{"learn":[0.2632155236],"iteration":858,"passed_time":7.946641845,"remaining_time":1.304396391},
{"learn":[0.2629277099],"iteration":859,"passed_time":7.95902755,"remaining_time":1.295655648},
{"learn":[0.2627721666],"iteration":860,"passed_time":7.968581498,"remaining_time":1.286449278},
{"learn":[0.262538198],"iteration":861,"passed_time":7.972262238,"remaining_time":1.276301843},
{"learn":[0.2622189549],"iteration":862,"passed_time":7.977470882,"remaining_time":1.266411948},
{"learn":[0.2619909054],"iteration":863,"passed_time":7.990859345,"remaining_time":1.257820452},
{"learn":[0.2618358179],"iteration":864,"passed_time":8.005157269,"remaining_time":1.249359805},
{"learn":[0.2616964452],"iteration":865,"passed_time":8.017173274,"remaining_time":1.240532585},
{"learn":[0.2613329932],"iteration":866,"passed_time":8.073717581,"remaining_time":1.238528764},
{"learn":[0.2610896301],"iteration":867,"passed_time":8.084634579,"remaining_time":1.229460558},
{"learn":[0.2609322491],"iteration":868,"passed_time":8.098204139,"remaining_time":1.220787966},
{"learn":[0.2606834499],"iteration":869,"passed_time":8.106275405,"remaining_time":1.211282532},
{"learn":[0.2604445103],"iteration":870,"passed_time":8.119909356,"remaining_time":1.202604256},
{"learn":[0.2602390062],"iteration":871,"passed_time":8.139475734,"remaining_time":1.194785429},
{"learn":[0.2598490859],"iteration":872,"passed_time":8.157501089,"remaining_time":1.186715508},
{"learn":[0.259713195],"iteration":873,"passed_time":8.172345751,"remaining_time":1.178164262},
{"learn":[0.2595165455],"iteration":874,"passed_time":8.190454156,"remaining_time":1.170064879},
{"learn":[0.2593245109],"iteration":875,"passed_time":8.199066967,"remaining_time":1.16059852},
{"learn":[0.2591815641],"iteration":876,"passed_time":8.211859331,"remaining_time":1.151720294},
{"learn":[0.2589394859],"iteration":877,"passed_time":8.220619229,"remaining_time":1.142272831},
{"learn":[0.2587659558],"iteration":878,"passed_time":8.226947658,"remaining_time":1.132492226},
{"learn":[0.2584813309],"iteration":879,"passed_time":8.235270558,"remaining_time":1.12299144},
{"learn":[0.2581914906],"iteration":880,"passed_time":8.288110641,"remaining_time":1.119506432},
{"learn":[0.2580501156],"iteration":881,"passed_time":8.300159306,"remaining_time":1.110452152},
{"learn":[0.2578668142],"iteration":882,"passed_time":8.3559587,"remaining_time":1.107188186},
{"learn":[0.2574977488],"iteration":883,"passed_time":8.370496621,"remaining_time":1.098390959},
{"learn":[0.257243567],"iteration":884,"passed_time":8.381531866,"remaining_time":1.08912561},
{"learn":[0.25704998],"iteration":885,"passed_time":8.397693385,"remaining_time":1.080515853},
{"learn":[0.2568195446],"iteration":886,"passed_time":8.411448565,"remaining_time":1.071582512},
{"learn":[0.2567105674],"iteration":887,"passed_time":8.445714792,"remaining_time":1.065225289},
{"learn":[0.2564085799],"iteration":888,"passed_time":8.4512876,"remaining_time":1.055222636},
{"learn":[0.2561958333],"iteration":889,"passed_time":8.456840193,"remaining_time":1.04522744},
{"learn":[0.2559704747],"iteration":890,"passed_time":8.46137742,"remaining_time":1.035118001},
{"learn":[0.2557180634],"iteration":891,"passed_time":8.468905964,"remaining_time":1.025383233},
{"learn":[0.2555466769],"iteration":892,"passed_time":8.473875165,"remaining_time":1.015346744},
{"learn":[0.2553460918],"iteration":893,"passed_time":8.477972782,"remaining_time":1.005218249},
{"learn":[0.2551127429],"iteration":894,"passed_time":8.507830173,"remaining_time":0.9981253276},
{"learn":[0.2548078663],"iteration":895,"passed_time":8.521584648,"remaining_time":0.9891125038},
{"learn":[0.2547545256],"iteration":896,"passed_time":8.525284812,"remaining_time":0.9789345993},
{"learn":[0.254345528],"iteration":897,"passed_time":8.531133139,"remaining_time":0.9690151227},
{"learn":[0.2542109467],"iteration":898,"passed_time":8.545525332,"remaining_time":0.9600645813},
{"learn":[0.2540034166],"iteration":899,"passed_time":8.550013352,"remaining_time":0.9500014835},
{"learn":[0.2538771315],"iteration":900,"passed_time":8.572687752,"remaining_time":0.9419490426},
{"learn":[0.2535664715],"iteration":901,"passed_time":8.5787998,"remaining_time":0.9320647232},
{"learn":[0.2534408757],"iteration":902,"passed_time":8.609070042,"remaining_time":0.9247838252},
{"learn":[0.2532137632],"iteration":903,"passed_time":8.620142238,"remaining_time":0.915413335},
{"learn":[0.2529359278],"iteration":904,"passed_time":8.625350422,"remaining_time":0.905423525},
{"learn":[0.2526654469],"iteration":905,"passed_time":8.631990185,"remaining_time":0.8955928006},
{"learn":[0.2524907363],"iteration":906,"passed_time":8.637095153,"remaining_time":0.8856117411},
{"learn":[0.2522817618],"iteration":907,"passed_time":8.650268845,"remaining_time":0.8764589579},
{"learn":[0.252115121],"iteration":908,"passed_time":8.664483403,"remaining_time":0.8674015288},
{"learn":[0.2517873788],"iteration":909,"passed_time":8.67233403,"remaining_time":0.8577033656},
{"learn":[0.2515660105],"iteration":910,"passed_time":8.686825662,"remaining_time":0.8486580504},
{"learn":[0.2513577938],"iteration":911,"passed_time":8.693329117,"remaining_time":0.8388300025},
{"learn":[0.2510778937],"iteration":912,"passed_time":8.698713751,"remaining_time":0.8289026247},
{"learn":[0.2508703697],"iteration":913,"passed_time":8.70826806,"remaining_time":0.8193775199},
{"learn":[0.2505430403],"iteration":914,"passed_time":8.712720881,"remaining_time":0.8093784425},
{"learn":[0.2503169035],"iteration":915,"passed_time":8.724917545,"remaining_time":0.8001016089},
{"learn":[0.2500343367],"iteration":916,"passed_time":8.733881836,"remaining_time":0.7905258369},
{"learn":[0.2498934385],"iteration":917,"passed_time":8.740171307,"remaining_time":0.7807124697},
{"learn":[0.249830815],"iteration":918,"passed_time":8.744150651,"remaining_time":0.7707031586},
{"learn":[0.2496498459],"iteration":919,"passed_time":8.780683728,"remaining_time":0.7635377155},
{"learn":[0.2494224647],"iteration":920,"passed_time":8.785346242,"remaining_time":0.7535747591},
{"learn":[0.2492047063],"iteration":921,"passed_time":8.80489502,"remaining_time":0.744882659},
{"learn":[0.2489929414],"iteration":922,"passed_time":8.822694613,"remaining_time":0.7360211108},
{"learn":[0.2486940915],"iteration":923,"passed_time":8.83532011,"remaining_time":0.7267146411},
{"learn":[0.248527619],"iteration":924,"passed_time":8.838974424,"remaining_time":0.716673602},
{"learn":[0.2482569587],"iteration":925,"passed_time":8.849538986,"remaining_time":0.7071985799},
{"learn":[0.2481040806],"iteration":926,"passed_time":8.853569229,"remaining_time":0.6972066383},
{"learn":[0.2478647773],"iteration":927,"passed_time":8.859462076,"remaining_time":0.6873720576},
{"learn":[0.2478121845],"iteration":928,"passed_time":8.863327722,"remaining_time":0.6773910315},
{"learn":[0.2475971988],"iteration":929,"passed_time":8.869572005,"remaining_time":0.6676021939},
{"learn":[0.2473558425],"iteration":930,"passed_time":8.877983102,"remaining_time":0.6579815618},
{"learn":[0.2471145149],"iteration":931,"passed_time":8.893011645,"remaining_time":0.6488463432},
{"learn":[0.2468816754],"iteration":932,"passed_time":8.930376418,"remaining_time":0.6413024866},
{"learn":[0.2466265995],"iteration":933,"passed_time":8.940984686,"remaining_time":0.631804057},
{"learn":[0.2463783688],"iteration":934,"passed_time":8.995352733,"remaining_time":0.6253453771},
{"learn":[0.2462390959],"iteration":935,"passed_time":8.998683007,"remaining_time":0.6152945646},
{"learn":[0.2459928261],"iteration":936,"passed_time":9.016664374,"remaining_time":0.6062431756},
{"learn":[0.2457317528],"iteration":937,"passed_time":9.043721067,"remaining_time":0.5977726078},
{"learn":[0.2455777785],"iteration":938,"passed_time":9.058551232,"remaining_time":0.5884681844},
{"learn":[0.2454206982],"iteration":939,"passed_time":9.06547393,"remaining_time":0.5786472721},
{"learn":[0.2451610858],"iteration":940,"passed_time":9.082051171,"remaining_time":0.5694378524},
{"learn":[0.244867662],"iteration":941,"passed_time":9.104803675,"remaining_time":0.5605930076},
{"learn":[0.2444965525],"iteration":942,"passed_time":9.116165814,"remaining_time":0.5510301712},
{"learn":[0.2442059765],"iteration":943,"passed_time":9.125634366,"remaining_time":0.5413511912},
{"learn":[0.2438638762],"iteration":944,"passed_time":9.130346645,"remaining_time":0.5313958365},
{"learn":[0.2435888907],"iteration":945,"passed_time":9.19940255,"remaining_time":0.5251244584},
{"learn":[0.2435831168],"iteration":946,"passed_time":9.205554263,"remaining_time":0.5151999746},
{"learn":[0.2433104708],"iteration":947,"passed_time":9.217863068,"remaining_time":0.505621181},
{"learn":[0.243062191],"iteration":948,"passed_time":9.221588439,"remaining_time":0.4955753534},
{"learn":[0.2428426516],"iteration":949,"passed_time":9.226579458,"remaining_time":0.4856094451},
{"learn":[0.2426428508],"iteration":950,"passed_time":9.235056749,"remaining_time":0.4758336285},
{"learn":[0.242489185],"iteration":951,"passed_time":9.242525408,"remaining_time":0.4660096844},
{"learn":[0.242265932],"iteration":952,"passed_time":9.266059178,"remaining_time":0.4569829815},
{"learn":[0.2420344888],"iteration":953,"passed_time":9.279701604,"remaining_time":0.4474489243},
{"learn":[0.241761419],"iteration":954,"passed_time":9.289456851,"remaining_time":0.4377230977},
{"learn":[0.2415722526],"iteration":955,"passed_time":9.294993048,"remaining_time":0.4278030273},
{"learn":[0.2414283416],"iteration":956,"passed_time":9.30865066,"remaining_time":0.4182570307},
{"learn":[0.2411993146],"iteration":957,"passed_time":9.31533046,"remaining_time":0.4083965337},
{"learn":[0.2409657256],"iteration":958,"passed_time":9.321018871,"remaining_time":0.3985002854},
{"learn":[0.2407013288],"iteration":959,"passed_time":9.325616702,"remaining_time":0.3885673626},
{"learn":[0.2406469948],"iteration":960,"passed_time":9.33164109,"remaining_time":0.3787034366},
{"learn":[0.2404232406],"iteration":961,"passed_time":9.340529683,"remaining_time":0.368960632},
{"learn":[0.240175926],"iteration":962,"passed_time":9.349447706,"remaining_time":0.3592207322},
{"learn":[0.2398926914],"iteration":963,"passed_time":9.360614832,"remaining_time":0.349566529},
{"learn":[0.2396714886],"iteration":964,"passed_time":9.401531343,"remaining_time":0.3409881834},
{"learn":[0.2396091791],"iteration":965,"passed_time":9.406068426,"remaining_time":0.3310624498},
{"learn":[0.2393766631],"iteration":966,"passed_time":9.411990494,"remaining_time":0.3211951254},
{"learn":[0.2391718151],"iteration":967,"passed_time":9.417080947,"remaining_time":0.3113084611},
{"learn":[0.2390341223],"iteration":968,"passed_time":9.421719355,"remaining_time":0.3014172343},
{"learn":[0.2388291574],"iteration":969,"passed_time":9.428365287,"remaining_time":0.2915989264},
{"learn":[0.2385322877],"iteration":970,"passed_time":9.456770818,"remaining_time":0.2824370275},
{"learn":[0.23831199],"iteration":971,"passed_time":9.461767124,"remaining_time":0.2725611929},
{"learn":[0.2380594688],"iteration":972,"passed_time":9.473435338,"remaining_time":0.2628805284},
{"learn":[0.2378139706],"iteration":973,"passed_time":9.488545632,"remaining_time":0.2532876657},
{"learn":[0.2376793888],"iteration":974,"passed_time":9.536136507,"remaining_time":0.2445163207},
{"learn":[0.2374662917],"iteration":975,"passed_time":9.547826163,"remaining_time":0.2347826106},
{"learn":[0.2372665096],"iteration":976,"passed_time":9.552140807,"remaining_time":0.2248712779},
{"learn":[0.2369993583],"iteration":977,"passed_time":9.565496501,"remaining_time":0.2151747679},
{"learn":[0.2366961003],"iteration":978,"passed_time":9.572837639,"remaining_time":0.2053417675},
{"learn":[0.2364440516],"iteration":979,"passed_time":9.579482263,"remaining_time":0.195499638},
{"learn":[0.2362305986],"iteration":980,"passed_time":9.583854754,"remaining_time":0.1856200207},
{"learn":[0.2359285962],"iteration":981,"passed_time":9.594099868,"remaining_time":0.1758592644},
{"learn":[0.2355740363],"iteration":982,"passed_time":9.600670522,"remaining_time":0.1660339765},
{"learn":[0.2354459542],"iteration":983,"passed_time":9.611250675,"remaining_time":0.1562804988},
{"learn":[0.2352894307],"iteration":984,"passed_time":9.616126334,"remaining_time":0.1464384721},
{"learn":[0.2349769203],"iteration":985,"passed_time":9.626503997,"remaining_time":0.1366846409},
{"learn":[0.2347245553],"iteration":986,"passed_time":9.637344273,"remaining_time":0.1269356388},
{"learn":[0.2346867549],"iteration":987,"passed_time":9.643384348,"remaining_time":0.1171261257},
{"learn":[0.2344950934],"iteration":988,"passed_time":9.6558273,"remaining_time":0.1073954503},
{"learn":[0.2342095381],"iteration":989,"passed_time":9.673777054,"remaining_time":0.09771491974},
{"learn":[0.234096292],"iteration":990,"passed_time":9.686014955,"remaining_time":0.08796582704},
{"learn":[0.2339867254],"iteration":991,"passed_time":9.697777009,"remaining_time":0.07820787911},
{"learn":[0.2338215328],"iteration":992,"passed_time":9.707575139,"remaining_time":0.06843205033},
{"learn":[0.2336261929],"iteration":993,"passed_time":9.723831066,"remaining_time":0.05869515734},
{"learn":[0.2335112972],"iteration":994,"passed_time":9.747886975,"remaining_time":0.04898435666},
{"learn":[0.2333214024],"iteration":995,"passed_time":9.753623322,"remaining_time":0.039171178},
{"learn":[0.2332187317],"iteration":996,"passed_time":9.767663756,"remaining_time":0.02939116476},
{"learn":[0.2330244184],"iteration":997,"passed_time":9.780169593,"remaining_time":0.01959953826},
{"learn":[0.2327865611],"iteration":998,"passed_time":9.797260879,"remaining_time":0.009807067947},
{"learn":[0.2326667204],"iteration":999,"passed_time":9.809523109,"remaining_time":0}
]}